Workbook

Sheet Extrato Mensal Jan
A2: REIS DO NORDESTE CAMA MESA E BANHO LTDA | B2: 05697368000174 | C2: CAMILA SILVA MOTA | D2: VENDEDOR (A) | E2: 72 | F2: Trabalhando | G2: 42438 | H2: 220:00 | I2: Salário: | J2: 1388.5
A3: REIS DO NORDESTE CAMA MESA E BANHO LTDA | B3: 05697368000174 | C3: CAMILA SILVA MOTA | D3: VENDEDOR (A) | E3: 72 | F3: Trabalhando | G3: 42438 | H3: 220:00 | I3: DESC.ADIANT.SALARIAL | J3: 555.4
A4: REIS DO NORDESTE CAMA MESA E BANHO LTDA | B4: 05697368000174 | C4: CAMILA SILVA MOTA | D4: VENDEDOR (A) | E4: 72 | F4: Trabalhando | G4: 42438 | H4: 220:00 | I4: I.N.S.S. | J4: 119.28
A5: REIS DO NORDESTE CAMA MESA E BANHO LTDA | B5: 05697368000174 | C5: CAMILA SILVA MOTA | D5: VENDEDOR (A) | E5: 72 | F5: Trabalhando | G5: 42438 | H5: 220:00 | I5: TRIENIO SINDCOMFS | J5: 138.85
A6: REIS DO NORDESTE CAMA MESA E BANHO LTDA | B6: 05697368000174 | C6: CAMILA SILVA MOTA | D6: VENDEDOR (A) | E6: 72 | F6: Trabalhando | G6: 42438 | H6: 220:00 | I6: VALES | J6: 29.99
A7: REIS DO NORDESTE CAMA MESA E BANHO LTDA | B7: 05697368000174 | C7: CAMILA SILVA MOTA | D7: VENDEDOR (A) | E7: 72 | F7: Trabalhando | G7: 42438 | H7: 220:00 | I7: VALE TRANSPORTE 6% | J7: 83.31
A8: REIS DO NORDESTE CAMA MESA E BANHO LTDA | B8: 05697368000174 | C8: ELIANE DOS SANTOS SILVA | D8: VENDEDOR (A) | E8: 100 | F8: Trabalhando | G8: 44117 | H8: 220:00 | I8: Salário: | J8: 1388.5
A9: REIS DO NORDESTE CAMA MESA E BANHO LTDA | B9: 05697368000174 | C9: ELIANE DOS SANTOS SILVA | D9: VENDEDOR (A) | E9: 100 | F9: Trabalhando | G9: 44117 | H9: 220:00 | I9: DESC.ADIANT.SALARIAL | J9: 555.4
A10: REIS DO NORDESTE CAMA MESA E BANHO LTDA | B10: 05697368000174 | C10: ELIANE DOS SANTOS SILVA | D10: VENDEDOR (A) | E10: 100 | F10: Trabalhando | G10: 44117 | H10: 220:00 | I10: I.N.S.S. | J10: 106.78
A11: REIS DO NORDESTE CAMA MESA E BANHO LTDA | B11: 05697368000174 | C11: ELIANE DOS SANTOS SILVA | D11: VENDEDOR (A) | E11: 100 | F11: Trabalhando | G11: 44117 | H11: 220:00 | I11: SALARIO FAMILIA | J11: 56.47
A12: REIS DO NORDESTE CAMA MESA E BANHO LTDA | B12: 05697368000174 | C12: ELIANE DOS SANTOS SILVA | D12: VENDEDOR (A) | E12: 100 | F12: Trabalhando | G12: 44117 | H12: 220:00 | I12: VALES | J12: 153.26
A13: REIS DO NORDESTE CAMA MESA E BANHO LTDA | B13: 05697368000174 | C13: ELIANE DOS SANTOS SILVA | D13: VENDEDOR (A) | E13: 100 | F13: Trabalhando | G13: 44117 | H13: 220:00 | I13: VALE TRANSPORTE 6% | J13: 83.31
... A592: REIS DO NORDESTE CAMA MESA E BANHO LTDA | B592: 05697368000336 | C592: VERONICA SANTOS DA SILVA | D592: COSTUREIRO ( A ) | E592: 145 | F592: Trabalhando | G592: 43497 | H592: 205:20 | I592: I.N.S.S. | J592: 90.9

Sheet Resumo
A1: SITUAÇÃO | B1: (Vários itens)
A2: Função | B2: (Vários itens)
A4: Rótulos de Linha | B4: SALARIO COM IMPOSTOS | C4: SALARIO BASE 2 | D4: BENEFICIOS | E4: VALE COMPRAS TOTAIS
A5: 5K DECORAÇÕES | B5: 6037.148 | C5: 1660 | D5: 99.6 | E5: 0 | G5: 6037.148 | H5: =G5-B5 -> 0
A6: GENESIS | B6: 31524.468 | C6: 500 | D6: 298.4 | E6: 101.99 | G6: 31524.468 | H6: =G6-B6 -> 0
A7: HOME CENTER | B7: 14455.508 | C7: 275 | D7: 139.2 | E7: 477 | G7: 14455.508 | H7: =G7-B7 -> 0
A8: MAISON | B8: 11647.063 | C8: 0 | D8: 238.86 | E8: 0 | G8: 11647.063 | H8: =G8-B8 -> 0
A9: ESCRITORIO | B9: 35779.316 | C9: 8156.364 | D9: 39.89 | E9: 126.78 | G9: 35779.316 | H9: =G9-B9 -> 0
A10: FABRICA | B10: 143386.03 | C10: 17011.62 | D10: 0 | E10: 0 | G10: 143386.03 | H10: =G10-B10 -> 0
A11: 30 K | B11: 16072.112 | C11: 632 | D11: -304.43 | E11: 299.67 | G11: 16072.112 | H11: =G11-B11 -> 0
A12: GRAND CANYON | B12: 12225.324 | C12: 2777 | D12: 0 | E12: 0 | G12: 12225.324 | H12: =G12-B12 -> 0
A13: 10k DECORAÇÕES | B13: 13049.936 | C13: 100 | D13: 0 | E13: 100 | G13: 13049.936 | H13: =G13-B13 -> 0
A14: AVANTE | B14: 12518.032 | C14: 0 | D14: -138 | E14: 188.27 | G14: 12518.032 | H14: =G14-B14 -> 0
A15: METANÓIA | B15: 11545.316 | C15: 0 | D15: 0 | E15: 0 | G15: 11545.316 | H15: =G15-B15 -> 0
A16: SR PASSOS | B16: 35640.921 | C16: 5275 | D16: 1452.55 | E16: 206.38 | G16: 43997.766 | H16: =G16-B16 -> 8356.8447
A17: 15 K COMERCIAL | B17: 10658.524 | C17: 0 | D17: -80 | E17: 360.42 | G17: 10658.524 | H17: =G17-B17 -> 0
A18: Total Geral | B18: 354539.69 | C18: 36386.984 | D18: 1746.07 | E18: 1860.51
G23: 0.01
G24: 0.08 | H24: =G24+G23 -> 0.09 | I24: =(H24-H23)/H23 -> #DIV/0!
G25: 0.28 | H25: =G25+H24 -> 0.37 | I25: =(H25-H24)/H24 -> 3.1111111
G26: 3.96 | H26: =G26+H25 -> 4.33 | I26: =(H26-H25)/H25 -> 10.702703
G27: 8.58 | H27: =G27+H26 -> 12.91 | I27: =(H27-H26)/H26 -> 1.9815242
G28: 7.21 | H28: =G28+H27 -> 20.12 | I28: =(H28-H27)/H27 -> 0.5584818
G29: 7.51 | H29: =G29+H28 -> 27.63 | I29: =(H29-H28)/H28 -> 0.37326044
G30: 8.1 | H30: =G30+H29 -> 35.73 | I30: =(H30-H29)/H29 -> 0.29315961
G31: 7.91 | H31: =G31+H30 -> 43.64 | I31: =(H31-H30)/H30 -> 0.22138259
G32: 9.07 | H32: =G32+H31 -> 52.71 | I32: =(H32-H31)/H31 -> 0.20783685
G33: 10.48 | H33: =G33+H32 -> 63.19 | I33: =(H33-H32)/H32 -> 0.19882375
G34: 11.85 | H34: =G34+H33 -> 75.04 | I34: =(H34-H33)/H33 -> 0.18752967
G35: 12.67 | H35: =G35+H34 -> 87.71 | I35: =(H35-H34)/H34 -> 0.16884328
G36: 16.35 | H36: =G36+H35 -> 104.06 | I36: =(H36-H35)/H35 -> 0.18640976
... G38: 18.63 | H38: =G38+H37 -> 138.69 | I38: =(H38-H37)/H37 -> 0.15517241
G39: 23.56 | H39: =G39+H38 -> 162.25 | I39: =(G39-G38)/G38 -> 0.26462695
G40: 24.32 | H40: =G40+H39 -> 186.57 | I40: =(G40-G39)/G39 -> 0.032258065
G44: =SUM(G23:G43) -> 186.57

Sheet GRATIFICAÇÃO
A1: COLABORADOR | B1: Função | C1: Razão Social | D1: Alocação | E1: Origem | F1: Valor Total | G1: Coluna1
A2: EDISLEY DA CONCEICAO | B2: FISCAL DE LOJA | C2: 05K | D2: REIS MATRIZ | E2: GRATIFICAÇÃO | F2: 300 | G2: =SUMIF(BASE_DE_NOMES[Nome],GRATIFICAÇÃO[[#This Row],[COLABORADOR]],BASE_DE_NOMES[GRATIFICAÇÃO])-GRATIFICAÇÃO[[#This Row],[Valor Total]] -> -300
A3: DANILO RIBEIRO SANTANA | B3: SERV.GERAIS | C3: REIS MATRIZ | D3: GENESIS | E3: GRATIFICAÇÃO | F3: 200 | G3: =SUMIF(BASE_DE_NOMES[Nome],GRATIFICAÇÃO[[#This Row],[COLABORADOR]],BASE_DE_NOMES[GRATIFICAÇÃO])-GRATIFICAÇÃO[[#This Row],[Valor Total]] -> 0
A4: DORIVALDO SANTOS ARAUJO | B4: CONFERENTE | C4: RAINHA HOME | D4: RAINHA HOME | E4: GRATIFICAÇÃO | F4: 275 | G4: =SUMIF(BASE_DE_NOMES[Nome],GRATIFICAÇÃO[[#This Row],[COLABORADOR]],BASE_DE_NOMES[GRATIFICAÇÃO])-GRATIFICAÇÃO[[#This Row],[Valor Total]] -> 0
A5: GILBERTO GALDINO DOS SANTOS | B5: SERVIÇOS GERAIS | C5: 10K | D5: 10K | E5: GRATIFICAÇÃO | F5: 100 | G5: =SUMIF(BASE_DE_NOMES[Nome],GRATIFICAÇÃO[[#This Row],[COLABORADOR]],BASE_DE_NOMES[GRATIFICAÇÃO])-GRATIFICAÇÃO[[#This Row],[Valor Total]] -> 0
A6: HEMILENE SOUZA RIBEIRO | B6: ASSIST FINAN | C6: REIS MATRIZ | D6: ESCRITÓRIO | E6: GRATIFICAÇÃO | F6: 300 | G6: =SUMIF(BASE_DE_NOMES[Nome],GRATIFICAÇÃO[[#This Row],[COLABORADOR]],BASE_DE_NOMES[GRATIFICAÇÃO])-GRATIFICAÇÃO[[#This Row],[Valor Total]] -> 0
A7: JOÃO VICTOR DE SOUZA | B7: SERVIÇOS GERAIS | C7: 05K | D7: RAINHA MAISON | E7: GRATIFICAÇÃO | F7: 150 | G7: =SUMIF(BASE_DE_NOMES[Nome],GRATIFICAÇÃO[[#This Row],[COLABORADOR]],BASE_DE_NOMES[GRATIFICAÇÃO])-GRATIFICAÇÃO[[#This Row],[Valor Total]] -> -150
A8: LEILANA FELICIANO SANTANA | B8: GERENTE | C8: GRAND CANYON | D8: GRAND CANYON | E8: GRATIFICAÇÃO | F8: 500 | G8: =SUMIF(BASE_DE_NOMES[Nome],GRATIFICAÇÃO[[#This Row],[COLABORADOR]],BASE_DE_NOMES[GRATIFICAÇÃO])-GRATIFICAÇÃO[[#This Row],[Valor Total]] -> 0
A9: NATERCIO PEREIRA SANTANA | B9: MOTORISTA | C9: REIS FABRICA | D9: REIS FABRICA | E9: GRATIFICAÇÃO | F9: 539 | G9: =SUMIF(BASE_DE_NOMES[Nome],GRATIFICAÇÃO[[#This Row],[COLABORADOR]],BASE_DE_NOMES[GRATIFICAÇÃO])-GRATIFICAÇÃO[[#This Row],[Valor Total]] -> 0
A10: UELITON DA SILVA DE JESUS | B10: SERVICOS GERAIS | C10: REIS MATRIZ | D10: REIS MATRIZ | E10: GRATIFICAÇÃO | F10: 300 | G10: =SUMIF(BASE_DE_NOMES[Nome],GRATIFICAÇÃO[[#This Row],[COLABORADOR]],BASE_DE_NOMES[GRATIFICAÇÃO])-GRATIFICAÇÃO[[#This Row],[Valor Total]] -> 0
A11: ALESSANDRO BATISTA DA ROCHA | B11: EMBALADOR | C11: REIS FÁBRICA | D11: REIS FÁBRICA | E11: GRATIFICAÇÃO | F11: 200 | G11: =SUMIF(BASE_DE_NOMES[Nome],GRATIFICAÇÃO[[#This Row],[COLABORADOR]],BASE_DE_NOMES[GRATIFICAÇÃO])-GRATIFICAÇÃO[[#This Row],[Valor Total]] -> 0
A12: ALBERTO DO NASCIMENTO SANTOS | B12: EMBALADOR | C12: REIS FÁBRICA | D12: REIS FÁBRICA | E12: GRATIFICAÇÃO | F12: 100 | G12: =SUMIF(BASE_DE_NOMES[Nome],GRATIFICAÇÃO[[#This Row],[COLABORADOR]],BASE_DE_NOMES[GRATIFICAÇÃO])-GRATIFICAÇÃO[[#This Row],[Valor Total]] -> 0
A13: FAGNER OLIVEIRA DOS SANTOS | B13: COORDENADOR | C13: VALE XEL | D13: VALE XEL | E13: GRATIFICAÇÃO | F13: 700 | G13: =SUMIF(BASE_DE_NOMES[Nome],GRATIFICAÇÃO[[#This Row],[COLABORADOR]],BASE_DE_NOMES[GRATIFICAÇÃO])-GRATIFICAÇÃO[[#This Row],[Valor Total]] -> 0
... A26: WILLIAM NASCIMENTO DOS SANTOS | B26: COSTUREIRO | C26: REIS FÁBRICA | D26: REIS FÁBRICA | E26: GRATIFICAÇÃO | F26: 200 | G26: =SUMIF(BASE_DE_NOMES[Nome],GRATIFICAÇÃO[[#This Row],[COLABORADOR]],BASE_DE_NOMES[GRATIFICAÇÃO])-GRATIFICAÇÃO[[#This Row],[Valor Total]] -> 0
F27: =SUBTOTAL(109,GRATIFICAÇÃO[Valor Total]) -> 7195 | G27: =SUBTOTAL(109,GRATIFICAÇÃO[Coluna1]) -> -1350

Sheet Salários Resumo (3)
A4: Situação | B4: (Vários itens)
A6: Soma de Total
A7: #NAME?

Sheet PG
A1: Nome | B1: Função | C1: Razão Social | D1: Alocação | E1: Valor Pago | F1: Coluna1
A2: DENIFER SANTOS DO NASCIMENTO - 15/05 | B2: APRENDIZ | C2: REIS FABRICA | D2: REIS FABRICA | E2: 379.5 | F2: =SUMIF(BASE_DE_NOMES[Nome],PG[[#This Row],[Nome]],BASE_DE_NOMES[PAGAMENTOS])-PG[[#This Row],[Valor Pago]] -> -379.5
A3: EDUARDA RODRIGUES | B3: APRENDIZ | C3: REIS FABRICA | D3: REIS FABRICA | E3: 1518 | F3: =SUMIF(BASE_DE_NOMES[Nome],PG[[#This Row],[Nome]],BASE_DE_NOMES[PAGAMENTOS])-PG[[#This Row],[Valor Pago]] -> -1518
A4: FERNANDA SANTOS | B4: APRENDIZ | C4: REIS FABRICA | D4: REIS FABRICA | E4: 759 | F4: =SUMIF(BASE_DE_NOMES[Nome],PG[[#This Row],[Nome]],BASE_DE_NOMES[PAGAMENTOS])-PG[[#This Row],[Valor Pago]] -> -759
A5: GILBERTO DOS SANTOS | B5: SUPERVISOR | C5: SEM REGISTRO | D5: REIS MATRIZ | E5: 5275 | F5: =SUMIF(BASE_DE_NOMES[Nome],PG[[#This Row],[Nome]],BASE_DE_NOMES[PAGAMENTOS])-PG[[#This Row],[Valor Pago]] -> 0
A6: ICAELLE NASCIMENTO GONZAGA | B6: APRENDIZ | C6: REIS FABRICA | D6: REIS FABRICA | E6: 759 | F6: =SUMIF(BASE_DE_NOMES[Nome],PG[[#This Row],[Nome]],BASE_DE_NOMES[PAGAMENTOS])-PG[[#This Row],[Valor Pago]] -> -759
A7: ISAC MORENO MENEZES MELO | B7: ASSIST. ADM | C7: SEM REGISTRO | D7: ESCRITORIO | E7: 2110 | F7: =SUMIF(BASE_DE_NOMES[Nome],PG[[#This Row],[Nome]],BASE_DE_NOMES[PAGAMENTOS])-PG[[#This Row],[Valor Pago]] -> 0
A8: IVONISE CARVALHO | B8: SERV GERAIS | C8: SEM REGISTRO | D8: ESCRITORIO | E8: 1016.474 | F8: =SUMIF(BASE_DE_NOMES[Nome],PG[[#This Row],[Nome]],BASE_DE_NOMES[PAGAMENTOS])-PG[[#This Row],[Valor Pago]] -> 0
A9: JILMAN DOS SANTOS | B9: GERENTE | C9: REIS FABRICA | D9: REIS FABRICA | E9: 821.44 | F9: =SUMIF(BASE_DE_NOMES[Nome],PG[[#This Row],[Nome]],BASE_DE_NOMES[PAGAMENTOS])-PG[[#This Row],[Valor Pago]] -> 0
A10: JOSE GABRIEL SANTOS SILVA | B10: APRENDIZ | C10: REIS FABRICA | D10: REIS FABRICA | E10: 759 | F10: =SUMIF(BASE_DE_NOMES[Nome],PG[[#This Row],[Nome]],BASE_DE_NOMES[PAGAMENTOS])-PG[[#This Row],[Valor Pago]] -> -759
A11: JOSE SOARES DOS SANTOS | B11: VIGIA | C11: REIS FABRICA | D11: REIS FABRICA | E11: 600 | F11: =SUMIF(BASE_DE_NOMES[Nome],PG[[#This Row],[Nome]],BASE_DE_NOMES[PAGAMENTOS])-PG[[#This Row],[Valor Pago]] -> -600
A12: JOÃO ANTONIO CUZ SANTANA | B12: APRENDIZ | C12: REIS FABRICA | D12: REIS FABRICA | E12: 759 | F12: =SUMIF(BASE_DE_NOMES[Nome],PG[[#This Row],[Nome]],BASE_DE_NOMES[PAGAMENTOS])-PG[[#This Row],[Valor Pago]] -> -759
A13: JULIA VILANOVA CANDIDO - 23/05 | B13: APRENDIZ | C13: REIS FABRICA | D13: REIS FABRICA | E13: 202.4 | F13: =SUMIF(BASE_DE_NOMES[Nome],PG[[#This Row],[Nome]],BASE_DE_NOMES[PAGAMENTOS])-PG[[#This Row],[Valor Pago]] -> -202.4
... A24: ROSILENE ROCHA DA SILVA - 16/05 | B24: APRENDIZ | C24: REIS FABRICA | D24: REIS FABRICA | E24: 354.2 | F24: =SUMIF(BASE_DE_NOMES[Nome],PG[[#This Row],[Nome]],BASE_DE_NOMES[PAGAMENTOS])-PG[[#This Row],[Valor Pago]] -> -354.2
A25: SHIRLEY CERQUEIRA PINTO | C25: SEM REGISTRO | D25: ESCRITORIO | E25: 3666.66 | F25: =SUMIF(BASE_DE_NOMES[Nome],PG[[#This Row],[Nome]],BASE_DE_NOMES[PAGAMENTOS])-PG[[#This Row],[Valor Pago]] -> 0
A26: VANDERSON LINO SANTOS | B26: APRENDIZ | C26: REIS FABRICA | D26: REIS FABRICA | E26: 50.6 | F26: =SUMIF(BASE_DE_NOMES[Nome],PG[[#This Row],[Nome]],BASE_DE_NOMES[PAGAMENTOS])-PG[[#This Row],[Valor Pago]] -> -50.6
A27: WALLAS FERREIRA DE SANTANA - 16/05 | B27: APRENDIZ | C27: REIS FABRICA | D27: REIS FABRICA | E27: 354.2 | F27: =SUMIF(BASE_DE_NOMES[Nome],PG[[#This Row],[Nome]],BASE_DE_NOMES[PAGAMENTOS])-PG[[#This Row],[Valor Pago]] -> -354.2
A28: WELLINGTON RIBEIRO | B28: COSTUREIRO | C28: SEM REGISTRO | D28: REIS FABRICA | E28: 1518 | F28: =SUMIF(BASE_DE_NOMES[Nome],PG[[#This Row],[Nome]],BASE_DE_NOMES[PAGAMENTOS])-PG[[#This Row],[Valor Pago]] -> -1518
E29: =SUBTOTAL(109,PG[Valor Pago]) -> 7590 | F29: =SUBTOTAL(109,PG[Coluna1]) -> -7590
H47: 0

Sheet Demitidos
A1: Index | B1: Column3 | C1: Column1
A2: 622 | B2: RAYANE MONTEIRO REIS | C2: 45746
A3: 655 | B3: VERONICA JESUS DOS SANTOS | C3: 45718
A4: 1393 | B4: COSMINHA PEREIRA COELHO | C4: 45718
A5: 1565 | B5: TAIUANA SANTOS SOARES | C5: 45718
A6: 1579 | B6: GILBERTO DOS SANTOS | C6: 45718
A7: 1593 | B7: IVONISE CARVALHO DE JESUS | C7: 45718
A8: 1612 | B8: JOELMA SILVA SANTOS | C8: 45718
A9: 1628 | B9: LAVINIA REIS DE LIMA | C9: 45718

Sheet BASE DE NOMES
A1: Nome | B1: Função | C1: Razão Social | D1: Alocações | E1: Admissão | F1: SITUAÇÃO | G1: C.CHEQUE | H1: FALTAS | I1: DESCONTO | J1: TOTAL DE C.CHEQUE | K1: GRATIFICAÇÃO | L1: PAGAMENTOS | M1: TOTAL DE QUEBRA | N1: ADC. ANTIGUIDADE | O1: TOTAL DE TRIENIO | P1: TX ASSIS. TOTAL | Q1: FAMILIA | R1: BOLSA DE AUXILIO | S1: VALE TRANSP | T1: PLANO DE SAUDE | U1: DESCONTOS | V1: BENEFICIOS | W1: VALE COMPRAS TOTAIS | X1: CCT | Y1: SALARIO BASE | Z1: SALARIO BASE 2 | AA1: IMPOSTOS | AB1: SALARIO COM IMPOSTOS | AC1: NOME2 | AD1: NOME3
A2: ADRIANA CLEIDE ALVES | B2: CAIXA | C2: 10K | D2: 10K | E2: =IFERROR(_xlfn.XLOOKUP(BASE_DE_NOMES[[#This Row],[Nome]],'Folha Rainha'!B:B,'Folha Rainha'!D:D),0) -> 0 | F2: =IFERROR(_xlfn.XLOOKUP(BASE_DE_NOMES[[#This Row],[Nome]],'Folha Rainha'!B:B,'Folha Rainha'!E:E)," ") | G2: =SUMIFS('Folha Rainha'!G:G,'Folha Rainha'!B:B,BASE_DE_NOMES[[#This Row],[Nome]],'Folha Rainha'!F:F,"Salário Base")+SUMIFS('Folha Rainha'!G:G,'Folha Rainha'!B:B,BASE_DE_NOMES[[#This Row],[Nome]],'Folha Rainha'!F:F,"Salário:") -> 0 | H2: =SUMIFS('Folha Rainha'!G:G,'Folha Rainha'!B:B,BASE_DE_NOMES[[#This Row],[Nome]],'Folha Rainha'!F:F,"HORAS FALTAS PARCIAL")+SUMIFS('Folha Rainha'!G:G,'Folha Rainha'!B:B,BASE_DE_NOMES[[#This Row],[Nome]],'Folha Rainha'!F:F,"HORAS FALTAS")+SUMIFS('Folha Rainha'!G:G,'Folha Rainha'!B:B,BASE_DE_NOMES[[#This Row],[Nome]],'Folha Rainha'!F:F,"HORAS FALTAS DSR")+SUMIFS('Folha Rainha'!G:G,'Folha Rainha'!B:B,BASE_DE_NOMES[[#This Row],[Nome]],'Folha Rainha'!F:F,"FALTA DE CAIXA") -> 0 | I2: =SUMIFS('Folha Rainha'!G:G,'Folha Rainha'!B:B,BASE_DE_NOMES[[#This Row],[Nome]],'Folha Rainha'!F:F,"DESCONTO HORAS AFASTADAS")+SUMIFS('Folha Rainha'!G:G,'Folha Rainha'!B:B,BASE_DE_NOMES[[#This Row],[Nome]],'Folha Rainha'!F:F,"DESCONTO HORAS AFASTADAS ACID TRABALHO")+SUMIFS('Folha Rainha'!G:G,'Folha Rainha'!B:B,BASE_DE_NOMES[[#This Row],[Nome]],'Folha Rainha'!F:F,"SALARIO MATERNIDADE") -> 0 | J2: =BASE_DE_NOMES[[#This Row],[C.CHEQUE]]-BASE_DE_NOMES[[#This Row],[FALTAS]]-BASE_DE_NOMES[[#This Row],[DESCONTO ]] -> 0 | K2: =SUMIF(GRATIFICAÇÃO!A:A,BASE_DE_NOMES[[#This Row],[Nome]],GRATIFICAÇÃO!F:F) -> 0 | L2: =SUMIF(PG!A:A,BASE_DE_NOMES[[#This Row],[Nome]],PG!E:E) -> 0 | M2: =SUMIFS('Folha Rainha'!G:G,'Folha Rainha'!B:B,BASE_DE_NOMES[[#This Row],[Nome]],'Folha Rainha'!F:F,"*Quebra*",'Folha Rainha'!F:F,"*QUEBRA*") -> 0 | N2: =SUMIFS('Folha Rainha'!G:G,'Folha Rainha'!B:B,BASE_DE_NOMES[[#This Row],[Nome]],'Folha Rainha'!F:F,"ADC. ANTIGUIDADE") -> 0 | O2: =SUMIFS('Folha Rainha'!G:G,'Folha Rainha'!B:B,BASE_DE_NOMES[[#This Row],[Nome]],'Folha Rainha'!F:F,"*Trienio*") -> 0 | P2: =SUMIFS('Folha Rainha'!G:G,'Folha Rainha'!B:B,BASE_DE_NOMES[[#This Row],[Nome]],'Folha Rainha'!F:F,"*TAXA*") -> 0 | Q2: =SUMIFS('Folha Rainha'!G:G,'Folha Rainha'!B:B,BASE_DE_NOMES[[#This Row],[Nome]],'Folha Rainha'!F:F,"SALARIO FAMILIA")+SUMIFS('Folha Rainha'!G:G,'Folha Rainha'!B:B,BASE_DE_NOMES[[#This Row],[Nome]],'Folha Rainha'!F:F,"Salário Família") -> 0 | R2: =SUMIFS('Folha Rainha'!G:G,'Folha Rainha'!B:B,BASE_DE_NOMES[[#This Row],[Nome]],'Folha Rainha'!F:F,"BOLSA AUXILIO")+SUMIFS('Folha Rainha'!G:G,'Folha Rainha'!B:B,BASE_DE_NOMES[[#This Row],[Nome]],'Folha Rainha'!F:F,"BOLSA AUXILIO AFASTAMENTO DIREITOS INT") -> 0 | S2: =SUMIFS('Folha Rainha'!G:G,'Folha Rainha'!B:B,BASE_DE_NOMES[[#This Row],[Nome]],'Folha Rainha'!F:F,"Vale Transporte")+SUMIFS('Folha Rainha'!G:G,'Folha Rainha'!B:B,BASE_DE_NOMES[[#This Row],[Nome]],'Folha Rainha'!F:F,"VALE TRANSPORTE 6%")+SUMIFS('Folha Rainha'!G:G,'Folha Rainha'!B:B,BASE_DE_NOMES[[#This Row],[Nome]],'Folha Rainha'!F:F,"AUXILIO TRANSPORTE ") -> 0 | T2: =SUMIFS('Folha Rainha'!G:G,'Folha Rainha'!B:B,BASE_DE_NOMES[[#This Row],[Nome]],'Folha Rainha'!F:F,"ASSISTÊNCIA ODONTOLÓGICA")+SUMIFS('Folha Rainha'!G:G,'Folha Rainha'!B:B,BASE_DE_NOMES[[#This Row],[Nome]],'Folha Rainha'!F:F,"ASSIST. ODONTO OUTROS DEPENDENTES")+SUMIFS('Folha Rainha'!G:G,'Folha Rainha'!B:B,BASE_DE_NOMES[[#This Row],[Nome]],'Folha Rainha'!F:F,"AUXILIO PLANO DE BENEFICIOS DEPENDENTES ") -> 0 | U2: =SUMIFS('Folha Rainha'!G:G,'Folha Rainha'!B:B,BASE_DE_NOMES[[#This Row],[Nome]],'Folha Rainha'!F:F,"BOLSA AUXILIO DESCONTO ADIANTAMENTO")+SUMIFS('Folha Rainha'!G:G,'Folha Rainha'!B:B,BASE_DE_NOMES[[#This Row],[Nome]],'Folha Rainha'!F:F,"DESCONTO PLANO DE SAÚDE")+BASE_DE_NOMES[[#This Row],[TX ASSIS. TOTAL]] -> 0 | V2: =BASE_DE_NOMES[[#This Row],[BOLSA DE AUXILIO]]+BASE_DE_NOMES[[#This Row],[VALE TRANSP]]+BASE_DE_NOMES[[#This Row],[PLANO DE SAUDE]]-BASE_DE_NOMES[[#This Row],[DESCONTOS]] -> 0 | W2: =SUMIFS('Folha Rainha'!G:G,'Folha Rainha'!B:B,BASE_DE_NOMES[[#This Row],[Nome]],'Folha Rainha'!F:F,"VALE COMPRAS")+SUMIFS('Folha Rainha'!G:G,'Folha Rainha'!B:B,BASE_DE_NOMES[[#This Row],[Nome]],'Folha Rainha'!F:F,"VALES") -> 0 | X2: =SUMIFS('Folha Rainha'!G:G,'Folha Rainha'!B:B,BASE_DE_NOMES[[#This Row],[Nome]],'Folha Rainha'!F:F,"ABONO CCT SECOFS 2024-2025")+SUMIFS('Folha Rainha'!G:G,'Folha Rainha'!B:B,BASE_DE_NOMES[[#This Row],[Nome]],'Folha Rainha'!F:F,"PARCELA DIFERENÇA 13o CCT")+SUMIFS('Folha Rainha'!G:G,'Folha Rainha'!B:B,BASE_DE_NOMES[[#This Row],[Nome]],'Folha Rainha'!F:F,"CONTRIBUICAO ABONO CCT 2024-2025") -> 0 | Y2: =BASE_DE_NOMES[[#This Row],[TOTAL DE C.CHEQUE]]+BASE_DE_NOMES[[#This Row],[TOTAL DE QUEBRA]]+BASE_DE_NOMES[[#This Row],[ADC. ANTIGUIDADE]]+BASE_DE_NOMES[[#This Row],[TOTAL DE TRIENIO]]+BASE_DE_NOMES[[#This Row],[CCT]] -> 0 | Z2: =BASE_DE_NOMES[[#This Row],[PAGAMENTOS]]+BASE_DE_NOMES[[#This Row],[GRATIFICAÇÃO]] -> 0 | AA2: =_xlfn.XLOOKUP(BASE_DE_NOMES[[#This Row],[NOME2]],Planilha1!C:C,Planilha1!D:D)*Y2 -> 0 | AB2: =BASE_DE_NOMES[[#This Row],[IMPOSTOS]]+BASE_DE_NOMES[[#This Row],[SALARIO BASE]]+BASE_DE_NOMES[[#This Row],[FAMILIA]] -> 0 | AC2: =_xlfn.XLOOKUP(BASE_DE_NOMES[[#This Row],[Razão Social]],Planilha1!B:B,Planilha1!C:C) -> 10k DECORAÇÕES | AD2: =_xlfn.XLOOKUP(BASE_DE_NOMES[[#This Row],[Alocações]],Planilha1!B:B,Planilha1!C:C) -> 10k DECORAÇÕES
A3: ADRIANE AMORIM RIBEIRO | B3: VENDEDOR | C3: GENESIS | D3: REIS MTZ | E3: =IFERROR(_xlfn.XLOOKUP(BASE_DE_NOMES[[#This Row],[Nome]],'Folha Rainha'!B:B,'Folha Rainha'!D:D),0) -> 0 | F3: =IFERROR(_xlfn.XLOOKUP(BASE_DE_NOMES[[#This Row],[Nome]],'Folha Rainha'!B:B,'Folha Rainha'!E:E)," ") | G3: =SUMIFS('Folha Rainha'!G:G,'Folha Rainha'!B:B,BASE_DE_NOMES[[#This Row],[Nome]],'Folha Rainha'!F:F,"Salário Base")+SUMIFS('Folha Rainha'!G:G,'Folha Rainha'!B:B,BASE_DE_NOMES[[#This Row],[Nome]],'Folha Rainha'!F:F,"Salário:") -> 0 | H3: =SUMIFS('Folha Rainha'!G:G,'Folha Rainha'!B:B,BASE_DE_NOMES[[#This Row],[Nome]],'Folha Rainha'!F:F,"HORAS FALTAS PARCIAL")+SUMIFS('Folha Rainha'!G:G,'Folha Rainha'!B:B,BASE_DE_NOMES[[#This Row],[Nome]],'Folha Rainha'!F:F,"HORAS FALTAS")+SUMIFS('Folha Rainha'!G:G,'Folha Rainha'!B:B,BASE_DE_NOMES[[#This Row],[Nome]],'Folha Rainha'!F:F,"HORAS FALTAS DSR")+SUMIFS('Folha Rainha'!G:G,'Folha Rainha'!B:B,BASE_DE_NOMES[[#This Row],[Nome]],'Folha Rainha'!F:F,"FALTA DE CAIXA") -> 0 | I3: =SUMIFS('Folha Rainha'!G:G,'Folha Rainha'!B:B,BASE_DE_NOMES[[#This Row],[Nome]],'Folha Rainha'!F:F,"DESCONTO HORAS AFASTADAS")+SUMIFS('Folha Rainha'!G:G,'Folha Rainha'!B:B,BASE_DE_NOMES[[#This Row],[Nome]],'Folha Rainha'!F:F,"DESCONTO HORAS AFASTADAS ACID TRABALHO")+SUMIFS('Folha Rainha'!G:G,'Folha Rainha'!B:B,BASE_DE_NOMES[[#This Row],[Nome]],'Folha Rainha'!F:F,"SALARIO MATERNIDADE") -> 0 | J3: =BASE_DE_NOMES[[#This Row],[C.CHEQUE]]-BASE_DE_NOMES[[#This Row],[FALTAS]]-BASE_DE_NOMES[[#This Row],[DESCONTO ]] -> 0 | K3: =SUMIF(GRATIFICAÇÃO!A:A,BASE_DE_NOMES[[#This Row],[Nome]],GRATIFICAÇÃO!F:F) -> 0 | L3: =SUMIF(PG!A:A,BASE_DE_NOMES[[#This Row],[Nome]],PG!E:E) -> 0 | M3: =SUMIFS('Folha Rainha'!G:G,'Folha Rainha'!B:B,BASE_DE_NOMES[[#This Row],[Nome]],'Folha Rainha'!F:F,"*Quebra*",'Folha Rainha'!F:F,"*QUEBRA*") -> 0 | N3: =SUMIFS('Folha Rainha'!G:G,'Folha Rainha'!B:B,BASE_DE_NOMES[[#This Row],[Nome]],'Folha Rainha'!F:F,"ADC. ANTIGUIDADE") -> 0 | O3: =SUMIFS('Folha Rainha'!G:G,'Folha Rainha'!B:B,BASE_DE_NOMES[[#This Row],[Nome]],'Folha Rainha'!F:F,"*Trienio*") -> 0 | P3: =SUMIFS('Folha Rainha'!G:G,'Folha Rainha'!B:B,BASE_DE_NOMES[[#This Row],[Nome]],'Folha Rainha'!F:F,"*TAXA*") -> 0 | Q3: =SUMIFS('Folha Rainha'!G:G,'Folha Rainha'!B:B,BASE_DE_NOMES[[#This Row],[Nome]],'Folha Rainha'!F:F,"SALARIO FAMILIA")+SUMIFS('Folha Rainha'!G:G,'Folha Rainha'!B:B,BASE_DE_NOMES[[#This Row],[Nome]],'Folha Rainha'!F:F,"Salário Família") -> 0 | R3: =SUMIFS('Folha Rainha'!G:G,'Folha Rainha'!B:B,BASE_DE_NOMES[[#This Row],[Nome]],'Folha Rainha'!F:F,"BOLSA AUXILIO")+SUMIFS('Folha Rainha'!G:G,'Folha Rainha'!B:B,BASE_DE_NOMES[[#This Row],[Nome]],'Folha Rainha'!F:F,"BOLSA AUXILIO AFASTAMENTO DIREITOS INT") -> 0 | S3: =SUMIFS('Folha Rainha'!G:G,'Folha Rainha'!B:B,BASE_DE_NOMES[[#This Row],[Nome]],'Folha Rainha'!F:F,"Vale Transporte")+SUMIFS('Folha Rainha'!G:G,'Folha Rainha'!B:B,BASE_DE_NOMES[[#This Row],[Nome]],'Folha Rainha'!F:F,"VALE TRANSPORTE 6%")+SUMIFS('Folha Rainha'!G:G,'Folha Rainha'!B:B,BASE_DE_NOMES[[#This Row],[Nome]],'Folha Rainha'!F:F,"AUXILIO TRANSPORTE ") -> 0 | T3: =SUMIFS('Folha Rainha'!G:G,'Folha Rainha'!B:B,BASE_DE_NOMES[[#This Row],[Nome]],'Folha Rainha'!F:F,"ASSISTÊNCIA ODONTOLÓGICA")+SUMIFS('Folha Rainha'!G:G,'Folha Rainha'!B:B,BASE_DE_NOMES[[#This Row],[Nome]],'Folha Rainha'!F:F,"ASSIST. ODONTO OUTROS DEPENDENTES")+SUMIFS('Folha Rainha'!G:G,'Folha Rainha'!B:B,BASE_DE_NOMES[[#This Row],[Nome]],'Folha Rainha'!F:F,"AUXILIO PLANO DE BENEFICIOS DEPENDENTES ") -> 0 | U3: =SUMIFS('Folha Rainha'!G:G,'Folha Rainha'!B:B,BASE_DE_NOMES[[#This Row],[Nome]],'Folha Rainha'!F:F,"BOLSA AUXILIO DESCONTO ADIANTAMENTO")+SUMIFS('Folha Rainha'!G:G,'Folha Rainha'!B:B,BASE_DE_NOMES[[#This Row],[Nome]],'Folha Rainha'!F:F,"DESCONTO PLANO DE SAÚDE")+BASE_DE_NOMES[[#This Row],[TX ASSIS. TOTAL]] -> 0 | V3: =BASE_DE_NOMES[[#This Row],[BOLSA DE AUXILIO]]+BASE_DE_NOMES[[#This Row],[VALE TRANSP]]+BASE_DE_NOMES[[#This Row],[PLANO DE SAUDE]]-BASE_DE_NOMES[[#This Row],[DESCONTOS]] -> 0 | W3: =SUMIFS('Folha Rainha'!G:G,'Folha Rainha'!B:B,BASE_DE_NOMES[[#This Row],[Nome]],'Folha Rainha'!F:F,"VALE COMPRAS")+SUMIFS('Folha Rainha'!G:G,'Folha Rainha'!B:B,BASE_DE_NOMES[[#This Row],[Nome]],'Folha Rainha'!F:F,"VALES") -> 0 | X3: =SUMIFS('Folha Rainha'!G:G,'Folha Rainha'!B:B,BASE_DE_NOMES[[#This Row],[Nome]],'Folha Rainha'!F:F,"ABONO CCT SECOFS 2024-2025")+SUMIFS('Folha Rainha'!G:G,'Folha Rainha'!B:B,BASE_DE_NOMES[[#This Row],[Nome]],'Folha Rainha'!F:F,"PARCELA DIFERENÇA 13o CCT")+SUMIFS('Folha Rainha'!G:G,'Folha Rainha'!B:B,BASE_DE_NOMES[[#This Row],[Nome]],'Folha Rainha'!F:F,"CONTRIBUICAO ABONO CCT 2024-2025") -> 0 | Y3: =BASE_DE_NOMES[[#This Row],[TOTAL DE C.CHEQUE]]+BASE_DE_NOMES[[#This Row],[TOTAL DE QUEBRA]]+BASE_DE_NOMES[[#This Row],[ADC. ANTIGUIDADE]]+BASE_DE_NOMES[[#This Row],[TOTAL DE TRIENIO]]+BASE_DE_NOMES[[#This Row],[CCT]] -> 0 | Z3: =BASE_DE_NOMES[[#This Row],[PAGAMENTOS]]+BASE_DE_NOMES[[#This Row],[GRATIFICAÇÃO]] -> 0 | AA3: =_xlfn.XLOOKUP(BASE_DE_NOMES[[#This Row],[NOME2]],Planilha1!C:C,Planilha1!D:D)*Y3 -> 0 | AB3: =BASE_DE_NOMES[[#This Row],[IMPOSTOS]]+BASE_DE_NOMES[[#This Row],[SALARIO BASE]]+BASE_DE_NOMES[[#This Row],[FAMILIA]] -> 0 | AC3: =_xlfn.XLOOKUP(BASE_DE_NOMES[[#This Row],[Razão Social]],Planilha1!B:B,Planilha1!C:C) -> GENESIS | AD3: =_xlfn.XLOOKUP(BASE_DE_NOMES[[#This Row],[Alocações]],Planilha1!B:B,Planilha1!C:C) -> SR PASSOS
A4: AILTON LUCENA | B4: GERENTE DE VENDAS | C4: GENESIS | D4: GENESIS | E4: =IFERROR(_xlfn.XLOOKUP(BASE_DE_NOMES[[#This Row],[Nome]],'Folha Rainha'!B:B,'Folha Rainha'!D:D),0) -> 39052 | F4: =IFERROR(_xlfn.XLOOKUP(BASE_DE_NOMES[[#This Row],[Nome]],'Folha Rainha'!B:B,'Folha Rainha'!E:E)," ") -> 0 | G4: =SUMIFS('Folha Rainha'!G:G,'Folha Rainha'!B:B,BASE_DE_NOMES[[#This Row],[Nome]],'Folha Rainha'!F:F,"Salário Base")+SUMIFS('Folha Rainha'!G:G,'Folha Rainha'!B:B,BASE_DE_NOMES[[#This Row],[Nome]],'Folha Rainha'!F:F,"Salário:") -> 4296.77 | H4: =SUMIFS('Folha Rainha'!G:G,'Folha Rainha'!B:B,BASE_DE_NOMES[[#This Row],[Nome]],'Folha Rainha'!F:F,"HORAS FALTAS PARCIAL")+SUMIFS('Folha Rainha'!G:G,'Folha Rainha'!B:B,BASE_DE_NOMES[[#This Row],[Nome]],'Folha Rainha'!F:F,"HORAS FALTAS")+SUMIFS('Folha Rainha'!G:G,'Folha Rainha'!B:B,BASE_DE_NOMES[[#This Row],[Nome]],'Folha Rainha'!F:F,"HORAS FALTAS DSR")+SUMIFS('Folha Rainha'!G:G,'Folha Rainha'!B:B,BASE_DE_NOMES[[#This Row],[Nome]],'Folha Rainha'!F:F,"FALTA DE CAIXA") -> 0 | I4: =SUMIFS('Folha Rainha'!G:G,'Folha Rainha'!B:B,BASE_DE_NOMES[[#This Row],[Nome]],'Folha Rainha'!F:F,"DESCONTO HORAS AFASTADAS")+SUMIFS('Folha Rainha'!G:G,'Folha Rainha'!B:B,BASE_DE_NOMES[[#This Row],[Nome]],'Folha Rainha'!F:F,"DESCONTO HORAS AFASTADAS ACID TRABALHO")+SUMIFS('Folha Rainha'!G:G,'Folha Rainha'!B:B,BASE_DE_NOMES[[#This Row],[Nome]],'Folha Rainha'!F:F,"SALARIO MATERNIDADE") -> 0 | J4: =BASE_DE_NOMES[[#This Row],[C.CHEQUE]]-BASE_DE_NOMES[[#This Row],[FALTAS]]-BASE_DE_NOMES[[#This Row],[DESCONTO ]] -> 4296.77 | K4: =SUMIF(GRATIFICAÇÃO!A:A,BASE_DE_NOMES[[#This Row],[Nome]],GRATIFICAÇÃO!F:F) -> 0 | L4: =SUMIF(PG!A:A,BASE_DE_NOMES[[#This Row],[Nome]],PG!E:E) -> 0 | M4: =SUMIFS('Folha Rainha'!G:G,'Folha Rainha'!B:B,BASE_DE_NOMES[[#This Row],[Nome]],'Folha Rainha'!F:F,"*Quebra*",'Folha Rainha'!F:F,"*QUEBRA*") -> 0 | N4: =SUMIFS('Folha Rainha'!G:G,'Folha Rainha'!B:B,BASE_DE_NOMES[[#This Row],[Nome]],'Folha Rainha'!F:F,"ADC. ANTIGUIDADE") -> 0 | O4: =SUMIFS('Folha Rainha'!G:G,'Folha Rainha'!B:B,BASE_DE_NOMES[[#This Row],[Nome]],'Folha Rainha'!F:F,"*Trienio*") -> 644.51 | P4: =SUMIFS('Folha Rainha'!G:G,'Folha Rainha'!B:B,BASE_DE_NOMES[[#This Row],[Nome]],'Folha Rainha'!F:F,"*TAXA*") -> 0 | Q4: =SUMIFS('Folha Rainha'!G:G,'Folha Rainha'!B:B,BASE_DE_NOMES[[#This Row],[Nome]],'Folha Rainha'!F:F,"SALARIO FAMILIA")+SUMIFS('Folha Rainha'!G:G,'Folha Rainha'!B:B,BASE_DE_NOMES[[#This Row],[Nome]],'Folha Rainha'!F:F,"Salário Família") -> 0 | R4: =SUMIFS('Folha Rainha'!G:G,'Folha Rainha'!B:B,BASE_DE_NOMES[[#This Row],[Nome]],'Folha Rainha'!F:F,"BOLSA AUXILIO")+SUMIFS('Folha Rainha'!G:G,'Folha Rainha'!B:B,BASE_DE_NOMES[[#This Row],[Nome]],'Folha Rainha'!F:F,"BOLSA AUXILIO AFASTAMENTO DIREITOS INT") -> 0 | S4: =SUMIFS('Folha Rainha'!G:G,'Folha Rainha'!B:B,BASE_DE_NOMES[[#This Row],[Nome]],'Folha Rainha'!F:F,"Vale Transporte")+SUMIFS('Folha Rainha'!G:G,'Folha Rainha'!B:B,BASE_DE_NOMES[[#This Row],[Nome]],'Folha Rainha'!F:F,"VALE TRANSPORTE 6%")+SUMIFS('Folha Rainha'!G:G,'Folha Rainha'!B:B,BASE_DE_NOMES[[#This Row],[Nome]],'Folha Rainha'!F:F,"AUXILIO TRANSPORTE ") -> 0 | T4: =SUMIFS('Folha Rainha'!G:G,'Folha Rainha'!B:B,BASE_DE_NOMES[[#This Row],[Nome]],'Folha Rainha'!F:F,"ASSISTÊNCIA ODONTOLÓGICA")+SUMIFS('Folha Rainha'!G:G,'Folha Rainha'!B:B,BASE_DE_NOMES[[#This Row],[Nome]],'Folha Rainha'!F:F,"ASSIST. ODONTO OUTROS DEPENDENTES")+SUMIFS('Folha Rainha'!G:G,'Folha Rainha'!B:B,BASE_DE_NOMES[[#This Row],[Nome]],'Folha Rainha'!F:F,"AUXILIO PLANO DE BENEFICIOS DEPENDENTES ") -> 0 | U4: =SUMIFS('Folha Rainha'!G:G,'Folha Rainha'!B:B,BASE_DE_NOMES[[#This Row],[Nome]],'Folha Rainha'!F:F,"BOLSA AUXILIO DESCONTO ADIANTAMENTO")+SUMIFS('Folha Rainha'!G:G,'Folha Rainha'!B:B,BASE_DE_NOMES[[#This Row],[Nome]],'Folha Rainha'!F:F,"DESCONTO PLANO DE SAÚDE")+BASE_DE_NOMES[[#This Row],[TX ASSIS. TOTAL]] -> 0 | V4: =BASE_DE_NOMES[[#This Row],[BOLSA DE AUXILIO]]+BASE_DE_NOMES[[#This Row],[VALE TRANSP]]+BASE_DE_NOMES[[#This Row],[PLANO DE SAUDE]]-BASE_DE_NOMES[[#This Row],[DESCONTOS]] -> 0 | W4: =SUMIFS('Folha Rainha'!G:G,'Folha Rainha'!B:B,BASE_DE_NOMES[[#This Row],[Nome]],'Folha Rainha'!F:F,"VALE COMPRAS")+SUMIFS('Folha Rainha'!G:G,'Folha Rainha'!B:B,BASE_DE_NOMES[[#This Row],[Nome]],'Folha Rainha'!F:F,"VALES") -> 0 | X4: =SUMIFS('Folha Rainha'!G:G,'Folha Rainha'!B:B,BASE_DE_NOMES[[#This Row],[Nome]],'Folha Rainha'!F:F,"ABONO CCT SECOFS 2024-2025")+SUMIFS('Folha Rainha'!G:G,'Folha Rainha'!B:B,BASE_DE_NOMES[[#This Row],[Nome]],'Folha Rainha'!F:F,"PARCELA DIFERENÇA 13o CCT")+SUMIFS('Folha Rainha'!G:G,'Folha Rainha'!B:B,BASE_DE_NOMES[[#This Row],[Nome]],'Folha Rainha'!F:F,"CONTRIBUICAO ABONO CCT 2024-2025") -> 0 | Y4: =BASE_DE_NOMES[[#This Row],[TOTAL DE C.CHEQUE]]+BASE_DE_NOMES[[#This Row],[TOTAL DE QUEBRA]]+BASE_DE_NOMES[[#This Row],[ADC. ANTIGUIDADE]]+BASE_DE_NOMES[[#This Row],[TOTAL DE TRIENIO]]+BASE_DE_NOMES[[#This Row],[CCT]] -> 4941.28 | Z4: =BASE_DE_NOMES[[#This Row],[PAGAMENTOS]]+BASE_DE_NOMES[[#This Row],[GRATIFICAÇÃO]] -> 0 | AA4: =_xlfn.XLOOKUP(BASE_DE_NOMES[[#This Row],[NOME2]],Planilha1!C:C,Planilha1!D:D)*Y4 -> 988.256 | AB4: =BASE_DE_NOMES[[#This Row],[IMPOSTOS]]+BASE_DE_NOMES[[#This Row],[SALARIO BASE]]+BASE_DE_NOMES[[#This Row],[FAMILIA]] -> 5929.536 | AC4: =_xlfn.XLOOKUP(BASE_DE_NOMES[[#This Row],[Razão Social]],Planilha1!B:B,Planilha1!C:C) -> GENESIS | AD4: =_xlfn.XLOOKUP(BASE_DE_NOMES[[#This Row],[Alocações]],Planilha1!B:B,Planilha1!C:C) -> GENESIS
A5: ALBERTO DO NASCIMENTO SANTOS | B5: EMBALADOR (A) | C5: REIS FÁBRICA | D5: REIS FÁBRICA | E5: =IFERROR(_xlfn.XLOOKUP(BASE_DE_NOMES[[#This Row],[Nome]],'Folha Rainha'!B:B,'Folha Rainha'!D:D),0) -> 43222 | F5: =IFERROR(_xlfn.XLOOKUP(BASE_DE_NOMES[[#This Row],[Nome]],'Folha Rainha'!B:B,'Folha Rainha'!E:E)," ") -> Férias | G5: =SUMIFS('Folha Rainha'!G:G,'Folha Rainha'!B:B,BASE_DE_NOMES[[#This Row],[Nome]],'Folha Rainha'!F:F,"Salário Base")+SUMIFS('Folha Rainha'!G:G,'Folha Rainha'!B:B,BASE_DE_NOMES[[#This Row],[Nome]],'Folha Rainha'!F:F,"Salário:") -> 1518 | H5: =SUMIFS('Folha Rainha'!G:G,'Folha Rainha'!B:B,BASE_DE_NOMES[[#This Row],[Nome]],'Folha Rainha'!F:F,"HORAS FALTAS PARCIAL")+SUMIFS('Folha Rainha'!G:G,'Folha Rainha'!B:B,BASE_DE_NOMES[[#This Row],[Nome]],'Folha Rainha'!F:F,"HORAS FALTAS")+SUMIFS('Folha Rainha'!G:G,'Folha Rainha'!B:B,BASE_DE_NOMES[[#This Row],[Nome]],'Folha Rainha'!F:F,"HORAS FALTAS DSR")+SUMIFS('Folha Rainha'!G:G,'Folha Rainha'!B:B,BASE_DE_NOMES[[#This Row],[Nome]],'Folha Rainha'!F:F,"FALTA DE CAIXA") -> 0 | I5: =SUMIFS('Folha Rainha'!G:G,'Folha Rainha'!B:B,BASE_DE_NOMES[[#This Row],[Nome]],'Folha Rainha'!F:F,"DESCONTO HORAS AFASTADAS")+SUMIFS('Folha Rainha'!G:G,'Folha Rainha'!B:B,BASE_DE_NOMES[[#This Row],[Nome]],'Folha Rainha'!F:F,"DESCONTO HORAS AFASTADAS ACID TRABALHO")+SUMIFS('Folha Rainha'!G:G,'Folha Rainha'!B:B,BASE_DE_NOMES[[#This Row],[Nome]],'Folha Rainha'!F:F,"SALARIO MATERNIDADE") -> 0 | J5: =BASE_DE_NOMES[[#This Row],[C.CHEQUE]]-BASE_DE_NOMES[[#This Row],[FALTAS]]-BASE_DE_NOMES[[#This Row],[DESCONTO ]] -> 1518 | K5: =SUMIF(GRATIFICAÇÃO!A:A,BASE_DE_NOMES[[#This Row],[Nome]],GRATIFICAÇÃO!F:F) -> 100 | L5: =SUMIF(PG!A:A,BASE_DE_NOMES[[#This Row],[Nome]],PG!E:E) -> 0 | M5: =SUMIFS('Folha Rainha'!G:G,'Folha Rainha'!B:B,BASE_DE_NOMES[[#This Row],[Nome]],'Folha Rainha'!F:F,"*Quebra*",'Folha Rainha'!F:F,"*QUEBRA*") -> 0 | N5: =SUMIFS('Folha Rainha'!G:G,'Folha Rainha'!B:B,BASE_DE_NOMES[[#This Row],[Nome]],'Folha Rainha'!F:F,"ADC. ANTIGUIDADE") -> 0 | O5: =SUMIFS('Folha Rainha'!G:G,'Folha Rainha'!B:B,BASE_DE_NOMES[[#This Row],[Nome]],'Folha Rainha'!F:F,"*Trienio*") -> 0 | P5: =SUMIFS('Folha Rainha'!G:G,'Folha Rainha'!B:B,BASE_DE_NOMES[[#This Row],[Nome]],'Folha Rainha'!F:F,"*TAXA*") -> 0 | Q5: =SUMIFS('Folha Rainha'!G:G,'Folha Rainha'!B:B,BASE_DE_NOMES[[#This Row],[Nome]],'Folha Rainha'!F:F,"SALARIO FAMILIA")+SUMIFS('Folha Rainha'!G:G,'Folha Rainha'!B:B,BASE_DE_NOMES[[#This Row],[Nome]],'Folha Rainha'!F:F,"Salário Família") -> 0 | R5: =SUMIFS('Folha Rainha'!G:G,'Folha Rainha'!B:B,BASE_DE_NOMES[[#This Row],[Nome]],'Folha Rainha'!F:F,"BOLSA AUXILIO")+SUMIFS('Folha Rainha'!G:G,'Folha Rainha'!B:B,BASE_DE_NOMES[[#This Row],[Nome]],'Folha Rainha'!F:F,"BOLSA AUXILIO AFASTAMENTO DIREITOS INT") -> 0 | S5: =SUMIFS('Folha Rainha'!G:G,'Folha Rainha'!B:B,BASE_DE_NOMES[[#This Row],[Nome]],'Folha Rainha'!F:F,"Vale Transporte")+SUMIFS('Folha Rainha'!G:G,'Folha Rainha'!B:B,BASE_DE_NOMES[[#This Row],[Nome]],'Folha Rainha'!F:F,"VALE TRANSPORTE 6%")+SUMIFS('Folha Rainha'!G:G,'Folha Rainha'!B:B,BASE_DE_NOMES[[#This Row],[Nome]],'Folha Rainha'!F:F,"AUXILIO TRANSPORTE ") -> 0 | T5: =SUMIFS('Folha Rainha'!G:G,'Folha Rainha'!B:B,BASE_DE_NOMES[[#This Row],[Nome]],'Folha Rainha'!F:F,"ASSISTÊNCIA ODONTOLÓGICA")+SUMIFS('Folha Rainha'!G:G,'Folha Rainha'!B:B,BASE_DE_NOMES[[#This Row],[Nome]],'Folha Rainha'!F:F,"ASSIST. ODONTO OUTROS DEPENDENTES")+SUMIFS('Folha Rainha'!G:G,'Folha Rainha'!B:B,BASE_DE_NOMES[[#This Row],[Nome]],'Folha Rainha'!F:F,"AUXILIO PLANO DE BENEFICIOS DEPENDENTES ") -> 0 | U5: =SUMIFS('Folha Rainha'!G:G,'Folha Rainha'!B:B,BASE_DE_NOMES[[#This Row],[Nome]],'Folha Rainha'!F:F,"BOLSA AUXILIO DESCONTO ADIANTAMENTO")+SUMIFS('Folha Rainha'!G:G,'Folha Rainha'!B:B,BASE_DE_NOMES[[#This Row],[Nome]],'Folha Rainha'!F:F,"DESCONTO PLANO DE SAÚDE")+BASE_DE_NOMES[[#This Row],[TX ASSIS. TOTAL]] -> 0 | V5: =BASE_DE_NOMES[[#This Row],[BOLSA DE AUXILIO]]+BASE_DE_NOMES[[#This Row],[VALE TRANSP]]+BASE_DE_NOMES[[#This Row],[PLANO DE SAUDE]]-BASE_DE_NOMES[[#This Row],[DESCONTOS]] -> 0 | W5: =SUMIFS('Folha Rainha'!G:G,'Folha Rainha'!B:B,BASE_DE_NOMES[[#This Row],[Nome]],'Folha Rainha'!F:F,"VALE COMPRAS")+SUMIFS('Folha Rainha'!G:G,'Folha Rainha'!B:B,BASE_DE_NOMES[[#This Row],[Nome]],'Folha Rainha'!F:F,"VALES") -> 0 | X5: =SUMIFS('Folha Rainha'!G:G,'Folha Rainha'!B:B,BASE_DE_NOMES[[#This Row],[Nome]],'Folha Rainha'!F:F,"ABONO CCT SECOFS 2024-2025")+SUMIFS('Folha Rainha'!G:G,'Folha Rainha'!B:B,BASE_DE_NOMES[[#This Row],[Nome]],'Folha Rainha'!F:F,"PARCELA DIFERENÇA 13o CCT")+SUMIFS('Folha Rainha'!G:G,'Folha Rainha'!B:B,BASE_DE_NOMES[[#This Row],[Nome]],'Folha Rainha'!F:F,"CONTRIBUICAO ABONO CCT 2024-2025") -> 0 | Y5: =BASE_DE_NOMES[[#This Row],[TOTAL DE C.CHEQUE]]+BASE_DE_NOMES[[#This Row],[TOTAL DE QUEBRA]]+BASE_DE_NOMES[[#This Row],[ADC. ANTIGUIDADE]]+BASE_DE_NOMES[[#This Row],[TOTAL DE TRIENIO]]+BASE_DE_NOMES[[#This Row],[CCT]] -> 1518 | Z5: =BASE_DE_NOMES[[#This Row],[PAGAMENTOS]]+BASE_DE_NOMES[[#This Row],[GRATIFICAÇÃO]] -> 100 | AA5: =_xlfn.XLOOKUP(BASE_DE_NOMES[[#This Row],[NOME2]],Planilha1!C:C,Planilha1!D:D)*Y5 -> 764.0094 | AB5: =BASE_DE_NOMES[[#This Row],[IMPOSTOS]]+BASE_DE_NOMES[[#This Row],[SALARIO BASE]]+BASE_DE_NOMES[[#This Row],[FAMILIA]] -> 2282.0094 | AC5: =_xlfn.XLOOKUP(BASE_DE_NOMES[[#This Row],[Razão Social]],Planilha1!B:B,Planilha1!C:C) -> FABRICA | AD5: =_xlfn.XLOOKUP(BASE_DE_NOMES[[#This Row],[Alocações]],Planilha1!B:B,Planilha1!C:C) -> FABRICA
A6: ALDA COITINHO DA SILVA | B6: VENDEDOR | C6: 05K | D6: GENESIS | E6: =IFERROR(_xlfn.XLOOKUP(BASE_DE_NOMES[[#This Row],[Nome]],'Folha Rainha'!B:B,'Folha Rainha'!D:D),0) -> 0 | F6: =IFERROR(_xlfn.XLOOKUP(BASE_DE_NOMES[[#This Row],[Nome]],'Folha Rainha'!B:B,'Folha Rainha'!E:E)," ") | G6: =SUMIFS('Folha Rainha'!G:G,'Folha Rainha'!B:B,BASE_DE_NOMES[[#This Row],[Nome]],'Folha Rainha'!F:F,"Salário Base")+SUMIFS('Folha Rainha'!G:G,'Folha Rainha'!B:B,BASE_DE_NOMES[[#This Row],[Nome]],'Folha Rainha'!F:F,"Salário:") -> 0 | H6: =SUMIFS('Folha Rainha'!G:G,'Folha Rainha'!B:B,BASE_DE_NOMES[[#This Row],[Nome]],'Folha Rainha'!F:F,"HORAS FALTAS PARCIAL")+SUMIFS('Folha Rainha'!G:G,'Folha Rainha'!B:B,BASE_DE_NOMES[[#This Row],[Nome]],'Folha Rainha'!F:F,"HORAS FALTAS")+SUMIFS('Folha Rainha'!G:G,'Folha Rainha'!B:B,BASE_DE_NOMES[[#This Row],[Nome]],'Folha Rainha'!F:F,"HORAS FALTAS DSR")+SUMIFS('Folha Rainha'!G:G,'Folha Rainha'!B:B,BASE_DE_NOMES[[#This Row],[Nome]],'Folha Rainha'!F:F,"FALTA DE CAIXA") -> 0 | I6: =SUMIFS('Folha Rainha'!G:G,'Folha Rainha'!B:B,BASE_DE_NOMES[[#This Row],[Nome]],'Folha Rainha'!F:F,"DESCONTO HORAS AFASTADAS")+SUMIFS('Folha Rainha'!G:G,'Folha Rainha'!B:B,BASE_DE_NOMES[[#This Row],[Nome]],'Folha Rainha'!F:F,"DESCONTO HORAS AFASTADAS ACID TRABALHO")+SUMIFS('Folha Rainha'!G:G,'Folha Rainha'!B:B,BASE_DE_NOMES[[#This Row],[Nome]],'Folha Rainha'!F:F,"SALARIO MATERNIDADE") -> 0 | J6: =BASE_DE_NOMES[[#This Row],[C.CHEQUE]]-BASE_DE_NOMES[[#This Row],[FALTAS]]-BASE_DE_NOMES[[#This Row],[DESCONTO ]] -> 0 | K6: =SUMIF(GRATIFICAÇÃO!A:A,BASE_DE_NOMES[[#This Row],[Nome]],GRATIFICAÇÃO!F:F) -> 0 | L6: =SUMIF(PG!A:A,BASE_DE_NOMES[[#This Row],[Nome]],PG!E:E) -> 0 | M6: =SUMIFS('Folha Rainha'!G:G,'Folha Rainha'!B:B,BASE_DE_NOMES[[#This Row],[Nome]],'Folha Rainha'!F:F,"*Quebra*",'Folha Rainha'!F:F,"*QUEBRA*") -> 0 | N6: =SUMIFS('Folha Rainha'!G:G,'Folha Rainha'!B:B,BASE_DE_NOMES[[#This Row],[Nome]],'Folha Rainha'!F:F,"ADC. ANTIGUIDADE") -> 0 | O6: =SUMIFS('Folha Rainha'!G:G,'Folha Rainha'!B:B,BASE_DE_NOMES[[#This Row],[Nome]],'Folha Rainha'!F:F,"*Trienio*") -> 0 | P6: =SUMIFS('Folha Rainha'!G:G,'Folha Rainha'!B:B,BASE_DE_NOMES[[#This Row],[Nome]],'Folha Rainha'!F:F,"*TAXA*") -> 0 | Q6: =SUMIFS('Folha Rainha'!G:G,'Folha Rainha'!B:B,BASE_DE_NOMES[[#This Row],[Nome]],'Folha Rainha'!F:F,"SALARIO FAMILIA")+SUMIFS('Folha Rainha'!G:G,'Folha Rainha'!B:B,BASE_DE_NOMES[[#This Row],[Nome]],'Folha Rainha'!F:F,"Salário Família") -> 0 | R6: =SUMIFS('Folha Rainha'!G:G,'Folha Rainha'!B:B,BASE_DE_NOMES[[#This Row],[Nome]],'Folha Rainha'!F:F,"BOLSA AUXILIO")+SUMIFS('Folha Rainha'!G:G,'Folha Rainha'!B:B,BASE_DE_NOMES[[#This Row],[Nome]],'Folha Rainha'!F:F,"BOLSA AUXILIO AFASTAMENTO DIREITOS INT") -> 0 | S6: =SUMIFS('Folha Rainha'!G:G,'Folha Rainha'!B:B,BASE_DE_NOMES[[#This Row],[Nome]],'Folha Rainha'!F:F,"Vale Transporte")+SUMIFS('Folha Rainha'!G:G,'Folha Rainha'!B:B,BASE_DE_NOMES[[#This Row],[Nome]],'Folha Rainha'!F:F,"VALE TRANSPORTE 6%")+SUMIFS('Folha Rainha'!G:G,'Folha Rainha'!B:B,BASE_DE_NOMES[[#This Row],[Nome]],'Folha Rainha'!F:F,"AUXILIO TRANSPORTE ") -> 0 | T6: =SUMIFS('Folha Rainha'!G:G,'Folha Rainha'!B:B,BASE_DE_NOMES[[#This Row],[Nome]],'Folha Rainha'!F:F,"ASSISTÊNCIA ODONTOLÓGICA")+SUMIFS('Folha Rainha'!G:G,'Folha Rainha'!B:B,BASE_DE_NOMES[[#This Row],[Nome]],'Folha Rainha'!F:F,"ASSIST. ODONTO OUTROS DEPENDENTES")+SUMIFS('Folha Rainha'!G:G,'Folha Rainha'!B:B,BASE_DE_NOMES[[#This Row],[Nome]],'Folha Rainha'!F:F,"AUXILIO PLANO DE BENEFICIOS DEPENDENTES ") -> 0 | U6: =SUMIFS('Folha Rainha'!G:G,'Folha Rainha'!B:B,BASE_DE_NOMES[[#This Row],[Nome]],'Folha Rainha'!F:F,"BOLSA AUXILIO DESCONTO ADIANTAMENTO")+SUMIFS('Folha Rainha'!G:G,'Folha Rainha'!B:B,BASE_DE_NOMES[[#This Row],[Nome]],'Folha Rainha'!F:F,"DESCONTO PLANO DE SAÚDE")+BASE_DE_NOMES[[#This Row],[TX ASSIS. TOTAL]] -> 0 | V6: =BASE_DE_NOMES[[#This Row],[BOLSA DE AUXILIO]]+BASE_DE_NOMES[[#This Row],[VALE TRANSP]]+BASE_DE_NOMES[[#This Row],[PLANO DE SAUDE]]-BASE_DE_NOMES[[#This Row],[DESCONTOS]] -> 0 | W6: =SUMIFS('Folha Rainha'!G:G,'Folha Rainha'!B:B,BASE_DE_NOMES[[#This Row],[Nome]],'Folha Rainha'!F:F,"VALE COMPRAS")+SUMIFS('Folha Rainha'!G:G,'Folha Rainha'!B:B,BASE_DE_NOMES[[#This Row],[Nome]],'Folha Rainha'!F:F,"VALES") -> 0 | X6: =SUMIFS('Folha Rainha'!G:G,'Folha Rainha'!B:B,BASE_DE_NOMES[[#This Row],[Nome]],'Folha Rainha'!F:F,"ABONO CCT SECOFS 2024-2025")+SUMIFS('Folha Rainha'!G:G,'Folha Rainha'!B:B,BASE_DE_NOMES[[#This Row],[Nome]],'Folha Rainha'!F:F,"PARCELA DIFERENÇA 13o CCT")+SUMIFS('Folha Rainha'!G:G,'Folha Rainha'!B:B,BASE_DE_NOMES[[#This Row],[Nome]],'Folha Rainha'!F:F,"CONTRIBUICAO ABONO CCT 2024-2025") -> 0 | Y6: =BASE_DE_NOMES[[#This Row],[TOTAL DE C.CHEQUE]]+BASE_DE_NOMES[[#This Row],[TOTAL DE QUEBRA]]+BASE_DE_NOMES[[#This Row],[ADC. ANTIGUIDADE]]+BASE_DE_NOMES[[#This Row],[TOTAL DE TRIENIO]]+BASE_DE_NOMES[[#This Row],[CCT]] -> 0 | Z6: =BASE_DE_NOMES[[#This Row],[PAGAMENTOS]]+BASE_DE_NOMES[[#This Row],[GRATIFICAÇÃO]] -> 0 | AA6: =_xlfn.XLOOKUP(BASE_DE_NOMES[[#This Row],[NOME2]],Planilha1!C:C,Planilha1!D:D)*Y6 -> 0 | AB6: =BASE_DE_NOMES[[#This Row],[IMPOSTOS]]+BASE_DE_NOMES[[#This Row],[SALARIO BASE]]+BASE_DE_NOMES[[#This Row],[FAMILIA]] -> 0 | AC6: =_xlfn.XLOOKUP(BASE_DE_NOMES[[#This Row],[Razão Social]],Planilha1!B:B,Planilha1!C:C) -> 5K DECORAÇÕES | AD6: =_xlfn.XLOOKUP(BASE_DE_NOMES[[#This Row],[Alocações]],Planilha1!B:B,Planilha1!C:C) -> GENESIS
A7: ALESSANDRO BATISTA DA ROCHA | B7: EMBALADOR (A) | C7: REIS FÁBRICA | D7: REIS FÁBRICA | E7: =IFERROR(_xlfn.XLOOKUP(BASE_DE_NOMES[[#This Row],[Nome]],'Folha Rainha'!B:B,'Folha Rainha'!D:D),0) -> 44637 | F7: =IFERROR(_xlfn.XLOOKUP(BASE_DE_NOMES[[#This Row],[Nome]],'Folha Rainha'!B:B,'Folha Rainha'!E:E)," ") -> Trabalhando | G7: =SUMIFS('Folha Rainha'!G:G,'Folha Rainha'!B:B,BASE_DE_NOMES[[#This Row],[Nome]],'Folha Rainha'!F:F,"Salário Base")+SUMIFS('Folha Rainha'!G:G,'Folha Rainha'!B:B,BASE_DE_NOMES[[#This Row],[Nome]],'Folha Rainha'!F:F,"Salário:") -> 1518 | H7: =SUMIFS('Folha Rainha'!G:G,'Folha Rainha'!B:B,BASE_DE_NOMES[[#This Row],[Nome]],'Folha Rainha'!F:F,"HORAS FALTAS PARCIAL")+SUMIFS('Folha Rainha'!G:G,'Folha Rainha'!B:B,BASE_DE_NOMES[[#This Row],[Nome]],'Folha Rainha'!F:F,"HORAS FALTAS")+SUMIFS('Folha Rainha'!G:G,'Folha Rainha'!B:B,BASE_DE_NOMES[[#This Row],[Nome]],'Folha Rainha'!F:F,"HORAS FALTAS DSR")+SUMIFS('Folha Rainha'!G:G,'Folha Rainha'!B:B,BASE_DE_NOMES[[#This Row],[Nome]],'Folha Rainha'!F:F,"FALTA DE CAIXA") -> 0 | I7: =SUMIFS('Folha Rainha'!G:G,'Folha Rainha'!B:B,BASE_DE_NOMES[[#This Row],[Nome]],'Folha Rainha'!F:F,"DESCONTO HORAS AFASTADAS")+SUMIFS('Folha Rainha'!G:G,'Folha Rainha'!B:B,BASE_DE_NOMES[[#This Row],[Nome]],'Folha Rainha'!F:F,"DESCONTO HORAS AFASTADAS ACID TRABALHO")+SUMIFS('Folha Rainha'!G:G,'Folha Rainha'!B:B,BASE_DE_NOMES[[#This Row],[Nome]],'Folha Rainha'!F:F,"SALARIO MATERNIDADE") -> 0 | J7: =BASE_DE_NOMES[[#This Row],[C.CHEQUE]]-BASE_DE_NOMES[[#This Row],[FALTAS]]-BASE_DE_NOMES[[#This Row],[DESCONTO ]] -> 1518 | K7: =SUMIF(GRATIFICAÇÃO!A:A,BASE_DE_NOMES[[#This Row],[Nome]],GRATIFICAÇÃO!F:F) -> 200 | L7: =SUMIF(PG!A:A,BASE_DE_NOMES[[#This Row],[Nome]],PG!E:E) -> 0 | M7: =SUMIFS('Folha Rainha'!G:G,'Folha Rainha'!B:B,BASE_DE_NOMES[[#This Row],[Nome]],'Folha Rainha'!F:F,"*Quebra*",'Folha Rainha'!F:F,"*QUEBRA*") -> 0 | N7: =SUMIFS('Folha Rainha'!G:G,'Folha Rainha'!B:B,BASE_DE_NOMES[[#This Row],[Nome]],'Folha Rainha'!F:F,"ADC. ANTIGUIDADE") -> 0 | O7: =SUMIFS('Folha Rainha'!G:G,'Folha Rainha'!B:B,BASE_DE_NOMES[[#This Row],[Nome]],'Folha Rainha'!F:F,"*Trienio*") -> 0 | P7: =SUMIFS('Folha Rainha'!G:G,'Folha Rainha'!B:B,BASE_DE_NOMES[[#This Row],[Nome]],'Folha Rainha'!F:F,"*TAXA*") -> 0 | Q7: =SUMIFS('Folha Rainha'!G:G,'Folha Rainha'!B:B,BASE_DE_NOMES[[#This Row],[Nome]],'Folha Rainha'!F:F,"SALARIO FAMILIA")+SUMIFS('Folha Rainha'!G:G,'Folha Rainha'!B:B,BASE_DE_NOMES[[#This Row],[Nome]],'Folha Rainha'!F:F,"Salário Família") -> 0 | R7: =SUMIFS('Folha Rainha'!G:G,'Folha Rainha'!B:B,BASE_DE_NOMES[[#This Row],[Nome]],'Folha Rainha'!F:F,"BOLSA AUXILIO")+SUMIFS('Folha Rainha'!G:G,'Folha Rainha'!B:B,BASE_DE_NOMES[[#This Row],[Nome]],'Folha Rainha'!F:F,"BOLSA AUXILIO AFASTAMENTO DIREITOS INT") -> 0 | S7: =SUMIFS('Folha Rainha'!G:G,'Folha Rainha'!B:B,BASE_DE_NOMES[[#This Row],[Nome]],'Folha Rainha'!F:F,"Vale Transporte")+SUMIFS('Folha Rainha'!G:G,'Folha Rainha'!B:B,BASE_DE_NOMES[[#This Row],[Nome]],'Folha Rainha'!F:F,"VALE TRANSPORTE 6%")+SUMIFS('Folha Rainha'!G:G,'Folha Rainha'!B:B,BASE_DE_NOMES[[#This Row],[Nome]],'Folha Rainha'!F:F,"AUXILIO TRANSPORTE ") -> 0 | T7: =SUMIFS('Folha Rainha'!G:G,'Folha Rainha'!B:B,BASE_DE_NOMES[[#This Row],[Nome]],'Folha Rainha'!F:F,"ASSISTÊNCIA ODONTOLÓGICA")+SUMIFS('Folha Rainha'!G:G,'Folha Rainha'!B:B,BASE_DE_NOMES[[#This Row],[Nome]],'Folha Rainha'!F:F,"ASSIST. ODONTO OUTROS DEPENDENTES")+SUMIFS('Folha Rainha'!G:G,'Folha Rainha'!B:B,BASE_DE_NOMES[[#This Row],[Nome]],'Folha Rainha'!F:F,"AUXILIO PLANO DE BENEFICIOS DEPENDENTES ") -> 0 | U7: =SUMIFS('Folha Rainha'!G:G,'Folha Rainha'!B:B,BASE_DE_NOMES[[#This Row],[Nome]],'Folha Rainha'!F:F,"BOLSA AUXILIO DESCONTO ADIANTAMENTO")+SUMIFS('Folha Rainha'!G:G,'Folha Rainha'!B:B,BASE_DE_NOMES[[#This Row],[Nome]],'Folha Rainha'!F:F,"DESCONTO PLANO DE SAÚDE")+BASE_DE_NOMES[[#This Row],[TX ASSIS. TOTAL]] -> 0 | V7: =BASE_DE_NOMES[[#This Row],[BOLSA DE AUXILIO]]+BASE_DE_NOMES[[#This Row],[VALE TRANSP]]+BASE_DE_NOMES[[#This Row],[PLANO DE SAUDE]]-BASE_DE_NOMES[[#This Row],[DESCONTOS]] -> 0 | W7: =SUMIFS('Folha Rainha'!G:G,'Folha Rainha'!B:B,BASE_DE_NOMES[[#This Row],[Nome]],'Folha Rainha'!F:F,"VALE COMPRAS")+SUMIFS('Folha Rainha'!G:G,'Folha Rainha'!B:B,BASE_DE_NOMES[[#This Row],[Nome]],'Folha Rainha'!F:F,"VALES") -> 0 | X7: =SUMIFS('Folha Rainha'!G:G,'Folha Rainha'!B:B,BASE_DE_NOMES[[#This Row],[Nome]],'Folha Rainha'!F:F,"ABONO CCT SECOFS 2024-2025")+SUMIFS('Folha Rainha'!G:G,'Folha Rainha'!B:B,BASE_DE_NOMES[[#This Row],[Nome]],'Folha Rainha'!F:F,"PARCELA DIFERENÇA 13o CCT")+SUMIFS('Folha Rainha'!G:G,'Folha Rainha'!B:B,BASE_DE_NOMES[[#This Row],[Nome]],'Folha Rainha'!F:F,"CONTRIBUICAO ABONO CCT 2024-2025") -> 0 | Y7: =BASE_DE_NOMES[[#This Row],[TOTAL DE C.CHEQUE]]+BASE_DE_NOMES[[#This Row],[TOTAL DE QUEBRA]]+BASE_DE_NOMES[[#This Row],[ADC. ANTIGUIDADE]]+BASE_DE_NOMES[[#This Row],[TOTAL DE TRIENIO]]+BASE_DE_NOMES[[#This Row],[CCT]] -> 1518 | Z7: =BASE_DE_NOMES[[#This Row],[PAGAMENTOS]]+BASE_DE_NOMES[[#This Row],[GRATIFICAÇÃO]] -> 200 | AA7: =_xlfn.XLOOKUP(BASE_DE_NOMES[[#This Row],[NOME2]],Planilha1!C:C,Planilha1!D:D)*Y7 -> 764.0094 | AB7: =BASE_DE_NOMES[[#This Row],[IMPOSTOS]]+BASE_DE_NOMES[[#This Row],[SALARIO BASE]]+BASE_DE_NOMES[[#This Row],[FAMILIA]] -> 2282.0094 | AC7: =_xlfn.XLOOKUP(BASE_DE_NOMES[[#This Row],[Razão Social]],Planilha1!B:B,Planilha1!C:C) -> FABRICA | AD7: =_xlfn.XLOOKUP(BASE_DE_NOMES[[#This Row],[Alocações]],Planilha1!B:B,Planilha1!C:C) -> FABRICA
A8: ALINE DE SOUZA SANTOS | B8: VENDEDOR | C8: 30K | D8: 30K | E8: =IFERROR(_xlfn.XLOOKUP(BASE_DE_NOMES[[#This Row],[Nome]],'Folha Rainha'!B:B,'Folha Rainha'!D:D),0) -> 45056 | F8: =IFERROR(_xlfn.XLOOKUP(BASE_DE_NOMES[[#This Row],[Nome]],'Folha Rainha'!B:B,'Folha Rainha'!E:E)," ") -> Trabalhando | G8: =SUMIFS('Folha Rainha'!G:G,'Folha Rainha'!B:B,BASE_DE_NOMES[[#This Row],[Nome]],'Folha Rainha'!F:F,"Salário Base")+SUMIFS('Folha Rainha'!G:G,'Folha Rainha'!B:B,BASE_DE_NOMES[[#This Row],[Nome]],'Folha Rainha'!F:F,"Salário:") -> 1607 | H8: =SUMIFS('Folha Rainha'!G:G,'Folha Rainha'!B:B,BASE_DE_NOMES[[#This Row],[Nome]],'Folha Rainha'!F:F,"HORAS FALTAS PARCIAL")+SUMIFS('Folha Rainha'!G:G,'Folha Rainha'!B:B,BASE_DE_NOMES[[#This Row],[Nome]],'Folha Rainha'!F:F,"HORAS FALTAS")+SUMIFS('Folha Rainha'!G:G,'Folha Rainha'!B:B,BASE_DE_NOMES[[#This Row],[Nome]],'Folha Rainha'!F:F,"HORAS FALTAS DSR")+SUMIFS('Folha Rainha'!G:G,'Folha Rainha'!B:B,BASE_DE_NOMES[[#This Row],[Nome]],'Folha Rainha'!F:F,"FALTA DE CAIXA") -> 0 | I8: =SUMIFS('Folha Rainha'!G:G,'Folha Rainha'!B:B,BASE_DE_NOMES[[#This Row],[Nome]],'Folha Rainha'!F:F,"DESCONTO HORAS AFASTADAS")+SUMIFS('Folha Rainha'!G:G,'Folha Rainha'!B:B,BASE_DE_NOMES[[#This Row],[Nome]],'Folha Rainha'!F:F,"DESCONTO HORAS AFASTADAS ACID TRABALHO")+SUMIFS('Folha Rainha'!G:G,'Folha Rainha'!B:B,BASE_DE_NOMES[[#This Row],[Nome]],'Folha Rainha'!F:F,"SALARIO MATERNIDADE") -> 0 | J8: =BASE_DE_NOMES[[#This Row],[C.CHEQUE]]-BASE_DE_NOMES[[#This Row],[FALTAS]]-BASE_DE_NOMES[[#This Row],[DESCONTO ]] -> 1607 | K8: =SUMIF(GRATIFICAÇÃO!A:A,BASE_DE_NOMES[[#This Row],[Nome]],GRATIFICAÇÃO!F:F) -> 0 | L8: =SUMIF(PG!A:A,BASE_DE_NOMES[[#This Row],[Nome]],PG!E:E) -> 0 | M8: =SUMIFS('Folha Rainha'!G:G,'Folha Rainha'!B:B,BASE_DE_NOMES[[#This Row],[Nome]],'Folha Rainha'!F:F,"*Quebra*",'Folha Rainha'!F:F,"*QUEBRA*") -> 0 | N8: =SUMIFS('Folha Rainha'!G:G,'Folha Rainha'!B:B,BASE_DE_NOMES[[#This Row],[Nome]],'Folha Rainha'!F:F,"ADC. ANTIGUIDADE") -> 0 | O8: =SUMIFS('Folha Rainha'!G:G,'Folha Rainha'!B:B,BASE_DE_NOMES[[#This Row],[Nome]],'Folha Rainha'!F:F,"*Trienio*") -> 0 | P8: =SUMIFS('Folha Rainha'!G:G,'Folha Rainha'!B:B,BASE_DE_NOMES[[#This Row],[Nome]],'Folha Rainha'!F:F,"*TAXA*") -> 0 | Q8: =SUMIFS('Folha Rainha'!G:G,'Folha Rainha'!B:B,BASE_DE_NOMES[[#This Row],[Nome]],'Folha Rainha'!F:F,"SALARIO FAMILIA")+SUMIFS('Folha Rainha'!G:G,'Folha Rainha'!B:B,BASE_DE_NOMES[[#This Row],[Nome]],'Folha Rainha'!F:F,"Salário Família") -> 0 | R8: =SUMIFS('Folha Rainha'!G:G,'Folha Rainha'!B:B,BASE_DE_NOMES[[#This Row],[Nome]],'Folha Rainha'!F:F,"BOLSA AUXILIO")+SUMIFS('Folha Rainha'!G:G,'Folha Rainha'!B:B,BASE_DE_NOMES[[#This Row],[Nome]],'Folha Rainha'!F:F,"BOLSA AUXILIO AFASTAMENTO DIREITOS INT") -> 0 | S8: =SUMIFS('Folha Rainha'!G:G,'Folha Rainha'!B:B,BASE_DE_NOMES[[#This Row],[Nome]],'Folha Rainha'!F:F,"Vale Transporte")+SUMIFS('Folha Rainha'!G:G,'Folha Rainha'!B:B,BASE_DE_NOMES[[#This Row],[Nome]],'Folha Rainha'!F:F,"VALE TRANSPORTE 6%")+SUMIFS('Folha Rainha'!G:G,'Folha Rainha'!B:B,BASE_DE_NOMES[[#This Row],[Nome]],'Folha Rainha'!F:F,"AUXILIO TRANSPORTE ") -> 0 | T8: =SUMIFS('Folha Rainha'!G:G,'Folha Rainha'!B:B,BASE_DE_NOMES[[#This Row],[Nome]],'Folha Rainha'!F:F,"ASSISTÊNCIA ODONTOLÓGICA")+SUMIFS('Folha Rainha'!G:G,'Folha Rainha'!B:B,BASE_DE_NOMES[[#This Row],[Nome]],'Folha Rainha'!F:F,"ASSIST. ODONTO OUTROS DEPENDENTES")+SUMIFS('Folha Rainha'!G:G,'Folha Rainha'!B:B,BASE_DE_NOMES[[#This Row],[Nome]],'Folha Rainha'!F:F,"AUXILIO PLANO DE BENEFICIOS DEPENDENTES ") -> 0 | U8: =SUMIFS('Folha Rainha'!G:G,'Folha Rainha'!B:B,BASE_DE_NOMES[[#This Row],[Nome]],'Folha Rainha'!F:F,"BOLSA AUXILIO DESCONTO ADIANTAMENTO")+SUMIFS('Folha Rainha'!G:G,'Folha Rainha'!B:B,BASE_DE_NOMES[[#This Row],[Nome]],'Folha Rainha'!F:F,"DESCONTO PLANO DE SAÚDE")+BASE_DE_NOMES[[#This Row],[TX ASSIS. TOTAL]] -> 0 | V8: =BASE_DE_NOMES[[#This Row],[BOLSA DE AUXILIO]]+BASE_DE_NOMES[[#This Row],[VALE TRANSP]]+BASE_DE_NOMES[[#This Row],[PLANO DE SAUDE]]-BASE_DE_NOMES[[#This Row],[DESCONTOS]] -> 0 | W8: =SUMIFS('Folha Rainha'!G:G,'Folha Rainha'!B:B,BASE_DE_NOMES[[#This Row],[Nome]],'Folha Rainha'!F:F,"VALE COMPRAS")+SUMIFS('Folha Rainha'!G:G,'Folha Rainha'!B:B,BASE_DE_NOMES[[#This Row],[Nome]],'Folha Rainha'!F:F,"VALES") -> 132.65 | X8: =SUMIFS('Folha Rainha'!G:G,'Folha Rainha'!B:B,BASE_DE_NOMES[[#This Row],[Nome]],'Folha Rainha'!F:F,"ABONO CCT SECOFS 2024-2025")+SUMIFS('Folha Rainha'!G:G,'Folha Rainha'!B:B,BASE_DE_NOMES[[#This Row],[Nome]],'Folha Rainha'!F:F,"PARCELA DIFERENÇA 13o CCT")+SUMIFS('Folha Rainha'!G:G,'Folha Rainha'!B:B,BASE_DE_NOMES[[#This Row],[Nome]],'Folha Rainha'!F:F,"CONTRIBUICAO ABONO CCT 2024-2025") -> 0 | Y8: =BASE_DE_NOMES[[#This Row],[TOTAL DE C.CHEQUE]]+BASE_DE_NOMES[[#This Row],[TOTAL DE QUEBRA]]+BASE_DE_NOMES[[#This Row],[ADC. ANTIGUIDADE]]+BASE_DE_NOMES[[#This Row],[TOTAL DE TRIENIO]]+BASE_DE_NOMES[[#This Row],[CCT]] -> 1607 | Z8: =BASE_DE_NOMES[[#This Row],[PAGAMENTOS]]+BASE_DE_NOMES[[#This Row],[GRATIFICAÇÃO]] -> 0 | AA8: =_xlfn.XLOOKUP(BASE_DE_NOMES[[#This Row],[NOME2]],Planilha1!C:C,Planilha1!D:D)*Y8 -> 321.4 | AB8: =BASE_DE_NOMES[[#This Row],[IMPOSTOS]]+BASE_DE_NOMES[[#This Row],[SALARIO BASE]]+BASE_DE_NOMES[[#This Row],[FAMILIA]] -> 1928.4 | AC8: =_xlfn.XLOOKUP(BASE_DE_NOMES[[#This Row],[Razão Social]],Planilha1!B:B,Planilha1!C:C) -> 30 K | AD8: =_xlfn.XLOOKUP(BASE_DE_NOMES[[#This Row],[Alocações]],Planilha1!B:B,Planilha1!C:C) -> 30 K
A9: ANA PAULA JESUS DOS SANTOS | B9: COSTUREIRO (A) | C9: REIS FÁBRICA | D9: REIS FÁBRICA | E9: =IFERROR(_xlfn.XLOOKUP(BASE_DE_NOMES[[#This Row],[Nome]],'Folha Rainha'!B:B,'Folha Rainha'!D:D),0) -> 45731 | F9: =IFERROR(_xlfn.XLOOKUP(BASE_DE_NOMES[[#This Row],[Nome]],'Folha Rainha'!B:B,'Folha Rainha'!E:E)," ") -> Trabalhando | G9: =SUMIFS('Folha Rainha'!G:G,'Folha Rainha'!B:B,BASE_DE_NOMES[[#This Row],[Nome]],'Folha Rainha'!F:F,"Salário Base")+SUMIFS('Folha Rainha'!G:G,'Folha Rainha'!B:B,BASE_DE_NOMES[[#This Row],[Nome]],'Folha Rainha'!F:F,"Salário:") -> 1518 | H9: =SUMIFS('Folha Rainha'!G:G,'Folha Rainha'!B:B,BASE_DE_NOMES[[#This Row],[Nome]],'Folha Rainha'!F:F,"HORAS FALTAS PARCIAL")+SUMIFS('Folha Rainha'!G:G,'Folha Rainha'!B:B,BASE_DE_NOMES[[#This Row],[Nome]],'Folha Rainha'!F:F,"HORAS FALTAS")+SUMIFS('Folha Rainha'!G:G,'Folha Rainha'!B:B,BASE_DE_NOMES[[#This Row],[Nome]],'Folha Rainha'!F:F,"HORAS FALTAS DSR")+SUMIFS('Folha Rainha'!G:G,'Folha Rainha'!B:B,BASE_DE_NOMES[[#This Row],[Nome]],'Folha Rainha'!F:F,"FALTA DE CAIXA") -> 0 | I9: =SUMIFS('Folha Rainha'!G:G,'Folha Rainha'!B:B,BASE_DE_NOMES[[#This Row],[Nome]],'Folha Rainha'!F:F,"DESCONTO HORAS AFASTADAS")+SUMIFS('Folha Rainha'!G:G,'Folha Rainha'!B:B,BASE_DE_NOMES[[#This Row],[Nome]],'Folha Rainha'!F:F,"DESCONTO HORAS AFASTADAS ACID TRABALHO")+SUMIFS('Folha Rainha'!G:G,'Folha Rainha'!B:B,BASE_DE_NOMES[[#This Row],[Nome]],'Folha Rainha'!F:F,"SALARIO MATERNIDADE") -> 0 | J9: =BASE_DE_NOMES[[#This Row],[C.CHEQUE]]-BASE_DE_NOMES[[#This Row],[FALTAS]]-BASE_DE_NOMES[[#This Row],[DESCONTO ]] -> 1518 | K9: =SUMIF(GRATIFICAÇÃO!A:A,BASE_DE_NOMES[[#This Row],[Nome]],GRATIFICAÇÃO!F:F) -> 0 | L9: =SUMIF(PG!A:A,BASE_DE_NOMES[[#This Row],[Nome]],PG!E:E) -> 0 | M9: =SUMIFS('Folha Rainha'!G:G,'Folha Rainha'!B:B,BASE_DE_NOMES[[#This Row],[Nome]],'Folha Rainha'!F:F,"*Quebra*",'Folha Rainha'!F:F,"*QUEBRA*") -> 0 | N9: =SUMIFS('Folha Rainha'!G:G,'Folha Rainha'!B:B,BASE_DE_NOMES[[#This Row],[Nome]],'Folha Rainha'!F:F,"ADC. ANTIGUIDADE") -> 0 | O9: =SUMIFS('Folha Rainha'!G:G,'Folha Rainha'!B:B,BASE_DE_NOMES[[#This Row],[Nome]],'Folha Rainha'!F:F,"*Trienio*") -> 0 | P9: =SUMIFS('Folha Rainha'!G:G,'Folha Rainha'!B:B,BASE_DE_NOMES[[#This Row],[Nome]],'Folha Rainha'!F:F,"*TAXA*") -> 0 | Q9: =SUMIFS('Folha Rainha'!G:G,'Folha Rainha'!B:B,BASE_DE_NOMES[[#This Row],[Nome]],'Folha Rainha'!F:F,"SALARIO FAMILIA")+SUMIFS('Folha Rainha'!G:G,'Folha Rainha'!B:B,BASE_DE_NOMES[[#This Row],[Nome]],'Folha Rainha'!F:F,"Salário Família") -> 0 | R9: =SUMIFS('Folha Rainha'!G:G,'Folha Rainha'!B:B,BASE_DE_NOMES[[#This Row],[Nome]],'Folha Rainha'!F:F,"BOLSA AUXILIO")+SUMIFS('Folha Rainha'!G:G,'Folha Rainha'!B:B,BASE_DE_NOMES[[#This Row],[Nome]],'Folha Rainha'!F:F,"BOLSA AUXILIO AFASTAMENTO DIREITOS INT") -> 0 | S9: =SUMIFS('Folha Rainha'!G:G,'Folha Rainha'!B:B,BASE_DE_NOMES[[#This Row],[Nome]],'Folha Rainha'!F:F,"Vale Transporte")+SUMIFS('Folha Rainha'!G:G,'Folha Rainha'!B:B,BASE_DE_NOMES[[#This Row],[Nome]],'Folha Rainha'!F:F,"VALE TRANSPORTE 6%")+SUMIFS('Folha Rainha'!G:G,'Folha Rainha'!B:B,BASE_DE_NOMES[[#This Row],[Nome]],'Folha Rainha'!F:F,"AUXILIO TRANSPORTE ") -> 0 | T9: =SUMIFS('Folha Rainha'!G:G,'Folha Rainha'!B:B,BASE_DE_NOMES[[#This Row],[Nome]],'Folha Rainha'!F:F,"ASSISTÊNCIA ODONTOLÓGICA")+SUMIFS('Folha Rainha'!G:G,'Folha Rainha'!B:B,BASE_DE_NOMES[[#This Row],[Nome]],'Folha Rainha'!F:F,"ASSIST. ODONTO OUTROS DEPENDENTES")+SUMIFS('Folha Rainha'!G:G,'Folha Rainha'!B:B,BASE_DE_NOMES[[#This Row],[Nome]],'Folha Rainha'!F:F,"AUXILIO PLANO DE BENEFICIOS DEPENDENTES ") -> 0 | U9: =SUMIFS('Folha Rainha'!G:G,'Folha Rainha'!B:B,BASE_DE_NOMES[[#This Row],[Nome]],'Folha Rainha'!F:F,"BOLSA AUXILIO DESCONTO ADIANTAMENTO")+SUMIFS('Folha Rainha'!G:G,'Folha Rainha'!B:B,BASE_DE_NOMES[[#This Row],[Nome]],'Folha Rainha'!F:F,"DESCONTO PLANO DE SAÚDE")+BASE_DE_NOMES[[#This Row],[TX ASSIS. TOTAL]] -> 0 | V9: =BASE_DE_NOMES[[#This Row],[BOLSA DE AUXILIO]]+BASE_DE_NOMES[[#This Row],[VALE TRANSP]]+BASE_DE_NOMES[[#This Row],[PLANO DE SAUDE]]-BASE_DE_NOMES[[#This Row],[DESCONTOS]] -> 0 | W9: =SUMIFS('Folha Rainha'!G:G,'Folha Rainha'!B:B,BASE_DE_NOMES[[#This Row],[Nome]],'Folha Rainha'!F:F,"VALE COMPRAS")+SUMIFS('Folha Rainha'!G:G,'Folha Rainha'!B:B,BASE_DE_NOMES[[#This Row],[Nome]],'Folha Rainha'!F:F,"VALES") -> 0 | X9: =SUMIFS('Folha Rainha'!G:G,'Folha Rainha'!B:B,BASE_DE_NOMES[[#This Row],[Nome]],'Folha Rainha'!F:F,"ABONO CCT SECOFS 2024-2025")+SUMIFS('Folha Rainha'!G:G,'Folha Rainha'!B:B,BASE_DE_NOMES[[#This Row],[Nome]],'Folha Rainha'!F:F,"PARCELA DIFERENÇA 13o CCT")+SUMIFS('Folha Rainha'!G:G,'Folha Rainha'!B:B,BASE_DE_NOMES[[#This Row],[Nome]],'Folha Rainha'!F:F,"CONTRIBUICAO ABONO CCT 2024-2025") -> 0 | Y9: =BASE_DE_NOMES[[#This Row],[TOTAL DE C.CHEQUE]]+BASE_DE_NOMES[[#This Row],[TOTAL DE QUEBRA]]+BASE_DE_NOMES[[#This Row],[ADC. ANTIGUIDADE]]+BASE_DE_NOMES[[#This Row],[TOTAL DE TRIENIO]]+BASE_DE_NOMES[[#This Row],[CCT]] -> 1518 | Z9: =BASE_DE_NOMES[[#This Row],[PAGAMENTOS]]+BASE_DE_NOMES[[#This Row],[GRATIFICAÇÃO]] -> 0 | AA9: =_xlfn.XLOOKUP(BASE_DE_NOMES[[#This Row],[NOME2]],Planilha1!C:C,Planilha1!D:D)*Y9 -> 764.0094 | AB9: =BASE_DE_NOMES[[#This Row],[IMPOSTOS]]+BASE_DE_NOMES[[#This Row],[SALARIO BASE]]+BASE_DE_NOMES[[#This Row],[FAMILIA]] -> 2282.0094 | AC9: =_xlfn.XLOOKUP(BASE_DE_NOMES[[#This Row],[Razão Social]],Planilha1!B:B,Planilha1!C:C) -> FABRICA | AD9: =_xlfn.XLOOKUP(BASE_DE_NOMES[[#This Row],[Alocações]],Planilha1!B:B,Planilha1!C:C) -> FABRICA
A10: ANA PAULA NEVES DA SILVA LEITE | B10: VENDEDOR | C10: RAINHA MAISON | D10: REIS MTZ | E10: =IFERROR(_xlfn.XLOOKUP(BASE_DE_NOMES[[#This Row],[Nome]],'Folha Rainha'!B:B,'Folha Rainha'!D:D),0) -> 44844 | F10: =IFERROR(_xlfn.XLOOKUP(BASE_DE_NOMES[[#This Row],[Nome]],'Folha Rainha'!B:B,'Folha Rainha'!E:E)," ") -> Trabalhando | G10: =SUMIFS('Folha Rainha'!G:G,'Folha Rainha'!B:B,BASE_DE_NOMES[[#This Row],[Nome]],'Folha Rainha'!F:F,"Salário Base")+SUMIFS('Folha Rainha'!G:G,'Folha Rainha'!B:B,BASE_DE_NOMES[[#This Row],[Nome]],'Folha Rainha'!F:F,"Salário:") -> 1660 | H10: =SUMIFS('Folha Rainha'!G:G,'Folha Rainha'!B:B,BASE_DE_NOMES[[#This Row],[Nome]],'Folha Rainha'!F:F,"HORAS FALTAS PARCIAL")+SUMIFS('Folha Rainha'!G:G,'Folha Rainha'!B:B,BASE_DE_NOMES[[#This Row],[Nome]],'Folha Rainha'!F:F,"HORAS FALTAS")+SUMIFS('Folha Rainha'!G:G,'Folha Rainha'!B:B,BASE_DE_NOMES[[#This Row],[Nome]],'Folha Rainha'!F:F,"HORAS FALTAS DSR")+SUMIFS('Folha Rainha'!G:G,'Folha Rainha'!B:B,BASE_DE_NOMES[[#This Row],[Nome]],'Folha Rainha'!F:F,"FALTA DE CAIXA") -> 0 | I10: =SUMIFS('Folha Rainha'!G:G,'Folha Rainha'!B:B,BASE_DE_NOMES[[#This Row],[Nome]],'Folha Rainha'!F:F,"DESCONTO HORAS AFASTADAS")+SUMIFS('Folha Rainha'!G:G,'Folha Rainha'!B:B,BASE_DE_NOMES[[#This Row],[Nome]],'Folha Rainha'!F:F,"DESCONTO HORAS AFASTADAS ACID TRABALHO")+SUMIFS('Folha Rainha'!G:G,'Folha Rainha'!B:B,BASE_DE_NOMES[[#This Row],[Nome]],'Folha Rainha'!F:F,"SALARIO MATERNIDADE") -> 0 | J10: =BASE_DE_NOMES[[#This Row],[C.CHEQUE]]-BASE_DE_NOMES[[#This Row],[FALTAS]]-BASE_DE_NOMES[[#This Row],[DESCONTO ]] -> 1660 | K10: =SUMIF(GRATIFICAÇÃO!A:A,BASE_DE_NOMES[[#This Row],[Nome]],GRATIFICAÇÃO!F:F) -> 0 | L10: =SUMIF(PG!A:A,BASE_DE_NOMES[[#This Row],[Nome]],PG!E:E) -> 0 | M10: =SUMIFS('Folha Rainha'!G:G,'Folha Rainha'!B:B,BASE_DE_NOMES[[#This Row],[Nome]],'Folha Rainha'!F:F,"*Quebra*",'Folha Rainha'!F:F,"*QUEBRA*") -> 0 | N10: =SUMIFS('Folha Rainha'!G:G,'Folha Rainha'!B:B,BASE_DE_NOMES[[#This Row],[Nome]],'Folha Rainha'!F:F,"ADC. ANTIGUIDADE") -> 0 | O10: =SUMIFS('Folha Rainha'!G:G,'Folha Rainha'!B:B,BASE_DE_NOMES[[#This Row],[Nome]],'Folha Rainha'!F:F,"*Trienio*") -> 0 | P10: =SUMIFS('Folha Rainha'!G:G,'Folha Rainha'!B:B,BASE_DE_NOMES[[#This Row],[Nome]],'Folha Rainha'!F:F,"*TAXA*") -> 0 | Q10: =SUMIFS('Folha Rainha'!G:G,'Folha Rainha'!B:B,BASE_DE_NOMES[[#This Row],[Nome]],'Folha Rainha'!F:F,"SALARIO FAMILIA")+SUMIFS('Folha Rainha'!G:G,'Folha Rainha'!B:B,BASE_DE_NOMES[[#This Row],[Nome]],'Folha Rainha'!F:F,"Salário Família") -> 0 | R10: =SUMIFS('Folha Rainha'!G:G,'Folha Rainha'!B:B,BASE_DE_NOMES[[#This Row],[Nome]],'Folha Rainha'!F:F,"BOLSA AUXILIO")+SUMIFS('Folha Rainha'!G:G,'Folha Rainha'!B:B,BASE_DE_NOMES[[#This Row],[Nome]],'Folha Rainha'!F:F,"BOLSA AUXILIO AFASTAMENTO DIREITOS INT") -> 0 | S10: =SUMIFS('Folha Rainha'!G:G,'Folha Rainha'!B:B,BASE_DE_NOMES[[#This Row],[Nome]],'Folha Rainha'!F:F,"Vale Transporte")+SUMIFS('Folha Rainha'!G:G,'Folha Rainha'!B:B,BASE_DE_NOMES[[#This Row],[Nome]],'Folha Rainha'!F:F,"VALE TRANSPORTE 6%")+SUMIFS('Folha Rainha'!G:G,'Folha Rainha'!B:B,BASE_DE_NOMES[[#This Row],[Nome]],'Folha Rainha'!F:F,"AUXILIO TRANSPORTE ") -> 99.6 | T10: =SUMIFS('Folha Rainha'!G:G,'Folha Rainha'!B:B,BASE_DE_NOMES[[#This Row],[Nome]],'Folha Rainha'!F:F,"ASSISTÊNCIA ODONTOLÓGICA")+SUMIFS('Folha Rainha'!G:G,'Folha Rainha'!B:B,BASE_DE_NOMES[[#This Row],[Nome]],'Folha Rainha'!F:F,"ASSIST. ODONTO OUTROS DEPENDENTES")+SUMIFS('Folha Rainha'!G:G,'Folha Rainha'!B:B,BASE_DE_NOMES[[#This Row],[Nome]],'Folha Rainha'!F:F,"AUXILIO PLANO DE BENEFICIOS DEPENDENTES ") -> 0 | U10: =SUMIFS('Folha Rainha'!G:G,'Folha Rainha'!B:B,BASE_DE_NOMES[[#This Row],[Nome]],'Folha Rainha'!F:F,"BOLSA AUXILIO DESCONTO ADIANTAMENTO")+SUMIFS('Folha Rainha'!G:G,'Folha Rainha'!B:B,BASE_DE_NOMES[[#This Row],[Nome]],'Folha Rainha'!F:F,"DESCONTO PLANO DE SAÚDE")+BASE_DE_NOMES[[#This Row],[TX ASSIS. TOTAL]] -> 0 | V10: =BASE_DE_NOMES[[#This Row],[BOLSA DE AUXILIO]]+BASE_DE_NOMES[[#This Row],[VALE TRANSP]]+BASE_DE_NOMES[[#This Row],[PLANO DE SAUDE]]-BASE_DE_NOMES[[#This Row],[DESCONTOS]] -> 99.6 | W10: =SUMIFS('Folha Rainha'!G:G,'Folha Rainha'!B:B,BASE_DE_NOMES[[#This Row],[Nome]],'Folha Rainha'!F:F,"VALE COMPRAS")+SUMIFS('Folha Rainha'!G:G,'Folha Rainha'!B:B,BASE_DE_NOMES[[#This Row],[Nome]],'Folha Rainha'!F:F,"VALES") -> 0 | X10: =SUMIFS('Folha Rainha'!G:G,'Folha Rainha'!B:B,BASE_DE_NOMES[[#This Row],[Nome]],'Folha Rainha'!F:F,"ABONO CCT SECOFS 2024-2025")+SUMIFS('Folha Rainha'!G:G,'Folha Rainha'!B:B,BASE_DE_NOMES[[#This Row],[Nome]],'Folha Rainha'!F:F,"PARCELA DIFERENÇA 13o CCT")+SUMIFS('Folha Rainha'!G:G,'Folha Rainha'!B:B,BASE_DE_NOMES[[#This Row],[Nome]],'Folha Rainha'!F:F,"CONTRIBUICAO ABONO CCT 2024-2025") -> 0 | Y10: =BASE_DE_NOMES[[#This Row],[TOTAL DE C.CHEQUE]]+BASE_DE_NOMES[[#This Row],[TOTAL DE QUEBRA]]+BASE_DE_NOMES[[#This Row],[ADC. ANTIGUIDADE]]+BASE_DE_NOMES[[#This Row],[TOTAL DE TRIENIO]]+BASE_DE_NOMES[[#This Row],[CCT]] -> 1660 | Z10: =BASE_DE_NOMES[[#This Row],[PAGAMENTOS]]+BASE_DE_NOMES[[#This Row],[GRATIFICAÇÃO]] -> 0 | AA10: =_xlfn.XLOOKUP(BASE_DE_NOMES[[#This Row],[NOME2]],Planilha1!C:C,Planilha1!D:D)*Y10 -> 332 | AB10: =BASE_DE_NOMES[[#This Row],[IMPOSTOS]]+BASE_DE_NOMES[[#This Row],[SALARIO BASE]]+BASE_DE_NOMES[[#This Row],[FAMILIA]] -> 1992 | AC10: =_xlfn.XLOOKUP(BASE_DE_NOMES[[#This Row],[Razão Social]],Planilha1!B:B,Planilha1!C:C) -> MAISON | AD10: =_xlfn.XLOOKUP(BASE_DE_NOMES[[#This Row],[Alocações]],Planilha1!B:B,Planilha1!C:C) -> SR PASSOS
A11: ANADILZA ALMEIDA SANTOS | B11: ENC DEPT PESSOAL | C11: 05K | D11: ESCRITORIO | E11: =IFERROR(_xlfn.XLOOKUP(BASE_DE_NOMES[[#This Row],[Nome]],'Folha Rainha'!B:B,'Folha Rainha'!D:D),0) -> 45458 | F11: =IFERROR(_xlfn.XLOOKUP(BASE_DE_NOMES[[#This Row],[Nome]],'Folha Rainha'!B:B,'Folha Rainha'!E:E)," ") -> Trabalhando | G11: =SUMIFS('Folha Rainha'!G:G,'Folha Rainha'!B:B,BASE_DE_NOMES[[#This Row],[Nome]],'Folha Rainha'!F:F,"Salário Base")+SUMIFS('Folha Rainha'!G:G,'Folha Rainha'!B:B,BASE_DE_NOMES[[#This Row],[Nome]],'Folha Rainha'!F:F,"Salário:") -> 3068.7 | H11: =SUMIFS('Folha Rainha'!G:G,'Folha Rainha'!B:B,BASE_DE_NOMES[[#This Row],[Nome]],'Folha Rainha'!F:F,"HORAS FALTAS PARCIAL")+SUMIFS('Folha Rainha'!G:G,'Folha Rainha'!B:B,BASE_DE_NOMES[[#This Row],[Nome]],'Folha Rainha'!F:F,"HORAS FALTAS")+SUMIFS('Folha Rainha'!G:G,'Folha Rainha'!B:B,BASE_DE_NOMES[[#This Row],[Nome]],'Folha Rainha'!F:F,"HORAS FALTAS DSR")+SUMIFS('Folha Rainha'!G:G,'Folha Rainha'!B:B,BASE_DE_NOMES[[#This Row],[Nome]],'Folha Rainha'!F:F,"FALTA DE CAIXA") -> 0 | I11: =SUMIFS('Folha Rainha'!G:G,'Folha Rainha'!B:B,BASE_DE_NOMES[[#This Row],[Nome]],'Folha Rainha'!F:F,"DESCONTO HORAS AFASTADAS")+SUMIFS('Folha Rainha'!G:G,'Folha Rainha'!B:B,BASE_DE_NOMES[[#This Row],[Nome]],'Folha Rainha'!F:F,"DESCONTO HORAS AFASTADAS ACID TRABALHO")+SUMIFS('Folha Rainha'!G:G,'Folha Rainha'!B:B,BASE_DE_NOMES[[#This Row],[Nome]],'Folha Rainha'!F:F,"SALARIO MATERNIDADE") -> 0 | J11: =BASE_DE_NOMES[[#This Row],[C.CHEQUE]]-BASE_DE_NOMES[[#This Row],[FALTAS]]-BASE_DE_NOMES[[#This Row],[DESCONTO ]] -> 3068.7 | K11: =SUMIF(GRATIFICAÇÃO!A:A,BASE_DE_NOMES[[#This Row],[Nome]],GRATIFICAÇÃO!F:F) -> 0 | L11: =SUMIF(PG!A:A,BASE_DE_NOMES[[#This Row],[Nome]],PG!E:E) -> 0 | M11: =SUMIFS('Folha Rainha'!G:G,'Folha Rainha'!B:B,BASE_DE_NOMES[[#This Row],[Nome]],'Folha Rainha'!F:F,"*Quebra*",'Folha Rainha'!F:F,"*QUEBRA*") -> 0 | N11: =SUMIFS('Folha Rainha'!G:G,'Folha Rainha'!B:B,BASE_DE_NOMES[[#This Row],[Nome]],'Folha Rainha'!F:F,"ADC. ANTIGUIDADE") -> 0 | O11: =SUMIFS('Folha Rainha'!G:G,'Folha Rainha'!B:B,BASE_DE_NOMES[[#This Row],[Nome]],'Folha Rainha'!F:F,"*Trienio*") -> 0 | P11: =SUMIFS('Folha Rainha'!G:G,'Folha Rainha'!B:B,BASE_DE_NOMES[[#This Row],[Nome]],'Folha Rainha'!F:F,"*TAXA*") -> 0 | Q11: =SUMIFS('Folha Rainha'!G:G,'Folha Rainha'!B:B,BASE_DE_NOMES[[#This Row],[Nome]],'Folha Rainha'!F:F,"SALARIO FAMILIA")+SUMIFS('Folha Rainha'!G:G,'Folha Rainha'!B:B,BASE_DE_NOMES[[#This Row],[Nome]],'Folha Rainha'!F:F,"Salário Família") -> 0 | R11: =SUMIFS('Folha Rainha'!G:G,'Folha Rainha'!B:B,BASE_DE_NOMES[[#This Row],[Nome]],'Folha Rainha'!F:F,"BOLSA AUXILIO")+SUMIFS('Folha Rainha'!G:G,'Folha Rainha'!B:B,BASE_DE_NOMES[[#This Row],[Nome]],'Folha Rainha'!F:F,"BOLSA AUXILIO AFASTAMENTO DIREITOS INT") -> 0 | S11: =SUMIFS('Folha Rainha'!G:G,'Folha Rainha'!B:B,BASE_DE_NOMES[[#This Row],[Nome]],'Folha Rainha'!F:F,"Vale Transporte")+SUMIFS('Folha Rainha'!G:G,'Folha Rainha'!B:B,BASE_DE_NOMES[[#This Row],[Nome]],'Folha Rainha'!F:F,"VALE TRANSPORTE 6%")+SUMIFS('Folha Rainha'!G:G,'Folha Rainha'!B:B,BASE_DE_NOMES[[#This Row],[Nome]],'Folha Rainha'!F:F,"AUXILIO TRANSPORTE ") -> 0 | T11: =SUMIFS('Folha Rainha'!G:G,'Folha Rainha'!B:B,BASE_DE_NOMES[[#This Row],[Nome]],'Folha Rainha'!F:F,"ASSISTÊNCIA ODONTOLÓGICA")+SUMIFS('Folha Rainha'!G:G,'Folha Rainha'!B:B,BASE_DE_NOMES[[#This Row],[Nome]],'Folha Rainha'!F:F,"ASSIST. ODONTO OUTROS DEPENDENTES")+SUMIFS('Folha Rainha'!G:G,'Folha Rainha'!B:B,BASE_DE_NOMES[[#This Row],[Nome]],'Folha Rainha'!F:F,"AUXILIO PLANO DE BENEFICIOS DEPENDENTES ") -> 0 | U11: =SUMIFS('Folha Rainha'!G:G,'Folha Rainha'!B:B,BASE_DE_NOMES[[#This Row],[Nome]],'Folha Rainha'!F:F,"BOLSA AUXILIO DESCONTO ADIANTAMENTO")+SUMIFS('Folha Rainha'!G:G,'Folha Rainha'!B:B,BASE_DE_NOMES[[#This Row],[Nome]],'Folha Rainha'!F:F,"DESCONTO PLANO DE SAÚDE")+BASE_DE_NOMES[[#This Row],[TX ASSIS. TOTAL]] -> 0 | V11: =BASE_DE_NOMES[[#This Row],[BOLSA DE AUXILIO]]+BASE_DE_NOMES[[#This Row],[VALE TRANSP]]+BASE_DE_NOMES[[#This Row],[PLANO DE SAUDE]]-BASE_DE_NOMES[[#This Row],[DESCONTOS]] -> 0 | W11: =SUMIFS('Folha Rainha'!G:G,'Folha Rainha'!B:B,BASE_DE_NOMES[[#This Row],[Nome]],'Folha Rainha'!F:F,"VALE COMPRAS")+SUMIFS('Folha Rainha'!G:G,'Folha Rainha'!B:B,BASE_DE_NOMES[[#This Row],[Nome]],'Folha Rainha'!F:F,"VALES") -> 0 | X11: =SUMIFS('Folha Rainha'!G:G,'Folha Rainha'!B:B,BASE_DE_NOMES[[#This Row],[Nome]],'Folha Rainha'!F:F,"ABONO CCT SECOFS 2024-2025")+SUMIFS('Folha Rainha'!G:G,'Folha Rainha'!B:B,BASE_DE_NOMES[[#This Row],[Nome]],'Folha Rainha'!F:F,"PARCELA DIFERENÇA 13o CCT")+SUMIFS('Folha Rainha'!G:G,'Folha Rainha'!B:B,BASE_DE_NOMES[[#This Row],[Nome]],'Folha Rainha'!F:F,"CONTRIBUICAO ABONO CCT 2024-2025") -> 0 | Y11: =BASE_DE_NOMES[[#This Row],[TOTAL DE C.CHEQUE]]+BASE_DE_NOMES[[#This Row],[TOTAL DE QUEBRA]]+BASE_DE_NOMES[[#This Row],[ADC. ANTIGUIDADE]]+BASE_DE_NOMES[[#This Row],[TOTAL DE TRIENIO]]+BASE_DE_NOMES[[#This Row],[CCT]] -> 3068.7 | Z11: =BASE_DE_NOMES[[#This Row],[PAGAMENTOS]]+BASE_DE_NOMES[[#This Row],[GRATIFICAÇÃO]] -> 0 | AA11: =_xlfn.XLOOKUP(BASE_DE_NOMES[[#This Row],[NOME2]],Planilha1!C:C,Planilha1!D:D)*Y11 -> 613.74 | AB11: =BASE_DE_NOMES[[#This Row],[IMPOSTOS]]+BASE_DE_NOMES[[#This Row],[SALARIO BASE]]+BASE_DE_NOMES[[#This Row],[FAMILIA]] -> 3682.44 | AC11: =_xlfn.XLOOKUP(BASE_DE_NOMES[[#This Row],[Razão Social]],Planilha1!B:B,Planilha1!C:C) -> 5K DECORAÇÕES | AD11: =_xlfn.XLOOKUP(BASE_DE_NOMES[[#This Row],[Alocações]],Planilha1!B:B,Planilha1!C:C) -> ESCRITORIO
A12: ANALIA GUIMARAES MARQUES | B12: GERENTE JUNIOR | C12: 15K | D12: 15K | E12: =IFERROR(_xlfn.XLOOKUP(BASE_DE_NOMES[[#This Row],[Nome]],'Folha Rainha'!B:B,'Folha Rainha'!D:D),0) -> 43437 | F12: =IFERROR(_xlfn.XLOOKUP(BASE_DE_NOMES[[#This Row],[Nome]],'Folha Rainha'!B:B,'Folha Rainha'!E:E)," ") -> Trabalhando | G12: =SUMIFS('Folha Rainha'!G:G,'Folha Rainha'!B:B,BASE_DE_NOMES[[#This Row],[Nome]],'Folha Rainha'!F:F,"Salário Base")+SUMIFS('Folha Rainha'!G:G,'Folha Rainha'!B:B,BASE_DE_NOMES[[#This Row],[Nome]],'Folha Rainha'!F:F,"Salário:") -> 2896.58 | H12: =SUMIFS('Folha Rainha'!G:G,'Folha Rainha'!B:B,BASE_DE_NOMES[[#This Row],[Nome]],'Folha Rainha'!F:F,"HORAS FALTAS PARCIAL")+SUMIFS('Folha Rainha'!G:G,'Folha Rainha'!B:B,BASE_DE_NOMES[[#This Row],[Nome]],'Folha Rainha'!F:F,"HORAS FALTAS")+SUMIFS('Folha Rainha'!G:G,'Folha Rainha'!B:B,BASE_DE_NOMES[[#This Row],[Nome]],'Folha Rainha'!F:F,"HORAS FALTAS DSR")+SUMIFS('Folha Rainha'!G:G,'Folha Rainha'!B:B,BASE_DE_NOMES[[#This Row],[Nome]],'Folha Rainha'!F:F,"FALTA DE CAIXA") -> 0 | I12: =SUMIFS('Folha Rainha'!G:G,'Folha Rainha'!B:B,BASE_DE_NOMES[[#This Row],[Nome]],'Folha Rainha'!F:F,"DESCONTO HORAS AFASTADAS")+SUMIFS('Folha Rainha'!G:G,'Folha Rainha'!B:B,BASE_DE_NOMES[[#This Row],[Nome]],'Folha Rainha'!F:F,"DESCONTO HORAS AFASTADAS ACID TRABALHO")+SUMIFS('Folha Rainha'!G:G,'Folha Rainha'!B:B,BASE_DE_NOMES[[#This Row],[Nome]],'Folha Rainha'!F:F,"SALARIO MATERNIDADE") -> 0 | J12: =BASE_DE_NOMES[[#This Row],[C.CHEQUE]]-BASE_DE_NOMES[[#This Row],[FALTAS]]-BASE_DE_NOMES[[#This Row],[DESCONTO ]] -> 2896.58 | K12: =SUMIF(GRATIFICAÇÃO!A:A,BASE_DE_NOMES[[#This Row],[Nome]],GRATIFICAÇÃO!F:F) -> 0 | L12: =SUMIF(PG!A:A,BASE_DE_NOMES[[#This Row],[Nome]],PG!E:E) -> 0 | M12: =SUMIFS('Folha Rainha'!G:G,'Folha Rainha'!B:B,BASE_DE_NOMES[[#This Row],[Nome]],'Folha Rainha'!F:F,"*Quebra*",'Folha Rainha'!F:F,"*QUEBRA*") -> 0 | N12: =SUMIFS('Folha Rainha'!G:G,'Folha Rainha'!B:B,BASE_DE_NOMES[[#This Row],[Nome]],'Folha Rainha'!F:F,"ADC. ANTIGUIDADE") -> 0 | O12: =SUMIFS('Folha Rainha'!G:G,'Folha Rainha'!B:B,BASE_DE_NOMES[[#This Row],[Nome]],'Folha Rainha'!F:F,"*Trienio*") -> 173.79 | P12: =SUMIFS('Folha Rainha'!G:G,'Folha Rainha'!B:B,BASE_DE_NOMES[[#This Row],[Nome]],'Folha Rainha'!F:F,"*TAXA*") -> 20 | Q12: =SUMIFS('Folha Rainha'!G:G,'Folha Rainha'!B:B,BASE_DE_NOMES[[#This Row],[Nome]],'Folha Rainha'!F:F,"SALARIO FAMILIA")+SUMIFS('Folha Rainha'!G:G,'Folha Rainha'!B:B,BASE_DE_NOMES[[#This Row],[Nome]],'Folha Rainha'!F:F,"Salário Família") -> 0 | R12: =SUMIFS('Folha Rainha'!G:G,'Folha Rainha'!B:B,BASE_DE_NOMES[[#This Row],[Nome]],'Folha Rainha'!F:F,"BOLSA AUXILIO")+SUMIFS('Folha Rainha'!G:G,'Folha Rainha'!B:B,BASE_DE_NOMES[[#This Row],[Nome]],'Folha Rainha'!F:F,"BOLSA AUXILIO AFASTAMENTO DIREITOS INT") -> 0 | S12: =SUMIFS('Folha Rainha'!G:G,'Folha Rainha'!B:B,BASE_DE_NOMES[[#This Row],[Nome]],'Folha Rainha'!F:F,"Vale Transporte")+SUMIFS('Folha Rainha'!G:G,'Folha Rainha'!B:B,BASE_DE_NOMES[[#This Row],[Nome]],'Folha Rainha'!F:F,"VALE TRANSPORTE 6%")+SUMIFS('Folha Rainha'!G:G,'Folha Rainha'!B:B,BASE_DE_NOMES[[#This Row],[Nome]],'Folha Rainha'!F:F,"AUXILIO TRANSPORTE ") -> 0 | T12: =SUMIFS('Folha Rainha'!G:G,'Folha Rainha'!B:B,BASE_DE_NOMES[[#This Row],[Nome]],'Folha Rainha'!F:F,"ASSISTÊNCIA ODONTOLÓGICA")+SUMIFS('Folha Rainha'!G:G,'Folha Rainha'!B:B,BASE_DE_NOMES[[#This Row],[Nome]],'Folha Rainha'!F:F,"ASSIST. ODONTO OUTROS DEPENDENTES")+SUMIFS('Folha Rainha'!G:G,'Folha Rainha'!B:B,BASE_DE_NOMES[[#This Row],[Nome]],'Folha Rainha'!F:F,"AUXILIO PLANO DE BENEFICIOS DEPENDENTES ") -> 0 | U12: =SUMIFS('Folha Rainha'!G:G,'Folha Rainha'!B:B,BASE_DE_NOMES[[#This Row],[Nome]],'Folha Rainha'!F:F,"BOLSA AUXILIO DESCONTO ADIANTAMENTO")+SUMIFS('Folha Rainha'!G:G,'Folha Rainha'!B:B,BASE_DE_NOMES[[#This Row],[Nome]],'Folha Rainha'!F:F,"DESCONTO PLANO DE SAÚDE")+BASE_DE_NOMES[[#This Row],[TX ASSIS. TOTAL]] -> 20 | V12: =BASE_DE_NOMES[[#This Row],[BOLSA DE AUXILIO]]+BASE_DE_NOMES[[#This Row],[VALE TRANSP]]+BASE_DE_NOMES[[#This Row],[PLANO DE SAUDE]]-BASE_DE_NOMES[[#This Row],[DESCONTOS]] -> -20 | W12: =SUMIFS('Folha Rainha'!G:G,'Folha Rainha'!B:B,BASE_DE_NOMES[[#This Row],[Nome]],'Folha Rainha'!F:F,"VALE COMPRAS")+SUMIFS('Folha Rainha'!G:G,'Folha Rainha'!B:B,BASE_DE_NOMES[[#This Row],[Nome]],'Folha Rainha'!F:F,"VALES") -> 45.15 | X12: =SUMIFS('Folha Rainha'!G:G,'Folha Rainha'!B:B,BASE_DE_NOMES[[#This Row],[Nome]],'Folha Rainha'!F:F,"ABONO CCT SECOFS 2024-2025")+SUMIFS('Folha Rainha'!G:G,'Folha Rainha'!B:B,BASE_DE_NOMES[[#This Row],[Nome]],'Folha Rainha'!F:F,"PARCELA DIFERENÇA 13o CCT")+SUMIFS('Folha Rainha'!G:G,'Folha Rainha'!B:B,BASE_DE_NOMES[[#This Row],[Nome]],'Folha Rainha'!F:F,"CONTRIBUICAO ABONO CCT 2024-2025") -> 0 | Y12: =BASE_DE_NOMES[[#This Row],[TOTAL DE C.CHEQUE]]+BASE_DE_NOMES[[#This Row],[TOTAL DE QUEBRA]]+BASE_DE_NOMES[[#This Row],[ADC. ANTIGUIDADE]]+BASE_DE_NOMES[[#This Row],[TOTAL DE TRIENIO]]+BASE_DE_NOMES[[#This Row],[CCT]] -> 3070.37 | Z12: =BASE_DE_NOMES[[#This Row],[PAGAMENTOS]]+BASE_DE_NOMES[[#This Row],[GRATIFICAÇÃO]] -> 0 | AA12: =_xlfn.XLOOKUP(BASE_DE_NOMES[[#This Row],[NOME2]],Planilha1!C:C,Planilha1!D:D)*Y12 -> 614.074 | AB12: =BASE_DE_NOMES[[#This Row],[IMPOSTOS]]+BASE_DE_NOMES[[#This Row],[SALARIO BASE]]+BASE_DE_NOMES[[#This Row],[FAMILIA]] -> 3684.444 | AC12: =_xlfn.XLOOKUP(BASE_DE_NOMES[[#This Row],[Razão Social]],Planilha1!B:B,Planilha1!C:C) -> 15 K COMERCIAL | AD12: =_xlfn.XLOOKUP(BASE_DE_NOMES[[#This Row],[Alocações]],Planilha1!B:B,Planilha1!C:C) -> 15 K COMERCIAL
A13: ANNE KAROLINA NASCIMENTO SANTOS | B13: VENDEDOR | C13: GRAND CANYON | D13: GRAND CANYON | E13: =IFERROR(_xlfn.XLOOKUP(BASE_DE_NOMES[[#This Row],[Nome]],'Folha Rainha'!B:B,'Folha Rainha'!D:D),0) -> 0 | F13: =IFERROR(_xlfn.XLOOKUP(BASE_DE_NOMES[[#This Row],[Nome]],'Folha Rainha'!B:B,'Folha Rainha'!E:E)," ") | G13: =SUMIFS('Folha Rainha'!G:G,'Folha Rainha'!B:B,BASE_DE_NOMES[[#This Row],[Nome]],'Folha Rainha'!F:F,"Salário Base")+SUMIFS('Folha Rainha'!G:G,'Folha Rainha'!B:B,BASE_DE_NOMES[[#This Row],[Nome]],'Folha Rainha'!F:F,"Salário:") -> 0 | H13: =SUMIFS('Folha Rainha'!G:G,'Folha Rainha'!B:B,BASE_DE_NOMES[[#This Row],[Nome]],'Folha Rainha'!F:F,"HORAS FALTAS PARCIAL")+SUMIFS('Folha Rainha'!G:G,'Folha Rainha'!B:B,BASE_DE_NOMES[[#This Row],[Nome]],'Folha Rainha'!F:F,"HORAS FALTAS")+SUMIFS('Folha Rainha'!G:G,'Folha Rainha'!B:B,BASE_DE_NOMES[[#This Row],[Nome]],'Folha Rainha'!F:F,"HORAS FALTAS DSR")+SUMIFS('Folha Rainha'!G:G,'Folha Rainha'!B:B,BASE_DE_NOMES[[#This Row],[Nome]],'Folha Rainha'!F:F,"FALTA DE CAIXA") -> 0 | I13: =SUMIFS('Folha Rainha'!G:G,'Folha Rainha'!B:B,BASE_DE_NOMES[[#This Row],[Nome]],'Folha Rainha'!F:F,"DESCONTO HORAS AFASTADAS")+SUMIFS('Folha Rainha'!G:G,'Folha Rainha'!B:B,BASE_DE_NOMES[[#This Row],[Nome]],'Folha Rainha'!F:F,"DESCONTO HORAS AFASTADAS ACID TRABALHO")+SUMIFS('Folha Rainha'!G:G,'Folha Rainha'!B:B,BASE_DE_NOMES[[#This Row],[Nome]],'Folha Rainha'!F:F,"SALARIO MATERNIDADE") -> 0 | J13: =BASE_DE_NOMES[[#This Row],[C.CHEQUE]]-BASE_DE_NOMES[[#This Row],[FALTAS]]-BASE_DE_NOMES[[#This Row],[DESCONTO ]] -> 0 | K13: =SUMIF(GRATIFICAÇÃO!A:A,BASE_DE_NOMES[[#This Row],[Nome]],GRATIFICAÇÃO!F:F) -> 0 | L13: =SUMIF(PG!A:A,BASE_DE_NOMES[[#This Row],[Nome]],PG!E:E) -> 0 | M13: =SUMIFS('Folha Rainha'!G:G,'Folha Rainha'!B:B,BASE_DE_NOMES[[#This Row],[Nome]],'Folha Rainha'!F:F,"*Quebra*",'Folha Rainha'!F:F,"*QUEBRA*") -> 0 | N13: =SUMIFS('Folha Rainha'!G:G,'Folha Rainha'!B:B,BASE_DE_NOMES[[#This Row],[Nome]],'Folha Rainha'!F:F,"ADC. ANTIGUIDADE") -> 0 | O13: =SUMIFS('Folha Rainha'!G:G,'Folha Rainha'!B:B,BASE_DE_NOMES[[#This Row],[Nome]],'Folha Rainha'!F:F,"*Trienio*") -> 0 | P13: =SUMIFS('Folha Rainha'!G:G,'Folha Rainha'!B:B,BASE_DE_NOMES[[#This Row],[Nome]],'Folha Rainha'!F:F,"*TAXA*") -> 0 | Q13: =SUMIFS('Folha Rainha'!G:G,'Folha Rainha'!B:B,BASE_DE_NOMES[[#This Row],[Nome]],'Folha Rainha'!F:F,"SALARIO FAMILIA")+SUMIFS('Folha Rainha'!G:G,'Folha Rainha'!B:B,BASE_DE_NOMES[[#This Row],[Nome]],'Folha Rainha'!F:F,"Salário Família") -> 0 | R13: =SUMIFS('Folha Rainha'!G:G,'Folha Rainha'!B:B,BASE_DE_NOMES[[#This Row],[Nome]],'Folha Rainha'!F:F,"BOLSA AUXILIO")+SUMIFS('Folha Rainha'!G:G,'Folha Rainha'!B:B,BASE_DE_NOMES[[#This Row],[Nome]],'Folha Rainha'!F:F,"BOLSA AUXILIO AFASTAMENTO DIREITOS INT") -> 0 | S13: =SUMIFS('Folha Rainha'!G:G,'Folha Rainha'!B:B,BASE_DE_NOMES[[#This Row],[Nome]],'Folha Rainha'!F:F,"Vale Transporte")+SUMIFS('Folha Rainha'!G:G,'Folha Rainha'!B:B,BASE_DE_NOMES[[#This Row],[Nome]],'Folha Rainha'!F:F,"VALE TRANSPORTE 6%")+SUMIFS('Folha Rainha'!G:G,'Folha Rainha'!B:B,BASE_DE_NOMES[[#This Row],[Nome]],'Folha Rainha'!F:F,"AUXILIO TRANSPORTE ") -> 0 | T13: =SUMIFS('Folha Rainha'!G:G,'Folha Rainha'!B:B,BASE_DE_NOMES[[#This Row],[Nome]],'Folha Rainha'!F:F,"ASSISTÊNCIA ODONTOLÓGICA")+SUMIFS('Folha Rainha'!G:G,'Folha Rainha'!B:B,BASE_DE_NOMES[[#This Row],[Nome]],'Folha Rainha'!F:F,"ASSIST. ODONTO OUTROS DEPENDENTES")+SUMIFS('Folha Rainha'!G:G,'Folha Rainha'!B:B,BASE_DE_NOMES[[#This Row],[Nome]],'Folha Rainha'!F:F,"AUXILIO PLANO DE BENEFICIOS DEPENDENTES ") -> 0 | U13: =SUMIFS('Folha Rainha'!G:G,'Folha Rainha'!B:B,BASE_DE_NOMES[[#This Row],[Nome]],'Folha Rainha'!F:F,"BOLSA AUXILIO DESCONTO ADIANTAMENTO")+SUMIFS('Folha Rainha'!G:G,'Folha Rainha'!B:B,BASE_DE_NOMES[[#This Row],[Nome]],'Folha Rainha'!F:F,"DESCONTO PLANO DE SAÚDE")+BASE_DE_NOMES[[#This Row],[TX ASSIS. TOTAL]] -> 0 | V13: =BASE_DE_NOMES[[#This Row],[BOLSA DE AUXILIO]]+BASE_DE_NOMES[[#This Row],[VALE TRANSP]]+BASE_DE_NOMES[[#This Row],[PLANO DE SAUDE]]-BASE_DE_NOMES[[#This Row],[DESCONTOS]] -> 0 | W13: =SUMIFS('Folha Rainha'!G:G,'Folha Rainha'!B:B,BASE_DE_NOMES[[#This Row],[Nome]],'Folha Rainha'!F:F,"VALE COMPRAS")+SUMIFS('Folha Rainha'!G:G,'Folha Rainha'!B:B,BASE_DE_NOMES[[#This Row],[Nome]],'Folha Rainha'!F:F,"VALES") -> 0 | X13: =SUMIFS('Folha Rainha'!G:G,'Folha Rainha'!B:B,BASE_DE_NOMES[[#This Row],[Nome]],'Folha Rainha'!F:F,"ABONO CCT SECOFS 2024-2025")+SUMIFS('Folha Rainha'!G:G,'Folha Rainha'!B:B,BASE_DE_NOMES[[#This Row],[Nome]],'Folha Rainha'!F:F,"PARCELA DIFERENÇA 13o CCT")+SUMIFS('Folha Rainha'!G:G,'Folha Rainha'!B:B,BASE_DE_NOMES[[#This Row],[Nome]],'Folha Rainha'!F:F,"CONTRIBUICAO ABONO CCT 2024-2025") -> 0 | Y13: =BASE_DE_NOMES[[#This Row],[TOTAL DE C.CHEQUE]]+BASE_DE_NOMES[[#This Row],[TOTAL DE QUEBRA]]+BASE_DE_NOMES[[#This Row],[ADC. ANTIGUIDADE]]+BASE_DE_NOMES[[#This Row],[TOTAL DE TRIENIO]]+BASE_DE_NOMES[[#This Row],[CCT]] -> 0 | Z13: =BASE_DE_NOMES[[#This Row],[PAGAMENTOS]]+BASE_DE_NOMES[[#This Row],[GRATIFICAÇÃO]] -> 0 | AA13: =_xlfn.XLOOKUP(BASE_DE_NOMES[[#This Row],[NOME2]],Planilha1!C:C,Planilha1!D:D)*Y13 -> 0 | AB13: =BASE_DE_NOMES[[#This Row],[IMPOSTOS]]+BASE_DE_NOMES[[#This Row],[SALARIO BASE]]+BASE_DE_NOMES[[#This Row],[FAMILIA]] -> 0 | AC13: =_xlfn.XLOOKUP(BASE_DE_NOMES[[#This Row],[Razão Social]],Planilha1!B:B,Planilha1!C:C) -> GRAND CANYON | AD13: =_xlfn.XLOOKUP(BASE_DE_NOMES[[#This Row],[Alocações]],Planilha1!B:B,Planilha1!C:C) -> GRAND CANYON
... A165: ZILDA DA MOTA LIMA | B165: VENDEDOR | C165: METANOIA | D165: METANOIA | E165: =IFERROR(_xlfn.XLOOKUP(BASE_DE_NOMES[[#This Row],[Nome]],'Folha Rainha'!B:B,'Folha Rainha'!D:D),0) -> 0 | F165: =IFERROR(_xlfn.XLOOKUP(BASE_DE_NOMES[[#This Row],[Nome]],'Folha Rainha'!B:B,'Folha Rainha'!E:E)," ") | G165: =SUMIFS('Folha Rainha'!G:G,'Folha Rainha'!B:B,BASE_DE_NOMES[[#This Row],[Nome]],'Folha Rainha'!F:F,"Salário Base")+SUMIFS('Folha Rainha'!G:G,'Folha Rainha'!B:B,BASE_DE_NOMES[[#This Row],[Nome]],'Folha Rainha'!F:F,"Salário:") -> 0 | H165: =SUMIFS('Folha Rainha'!G:G,'Folha Rainha'!B:B,BASE_DE_NOMES[[#This Row],[Nome]],'Folha Rainha'!F:F,"HORAS FALTAS PARCIAL")+SUMIFS('Folha Rainha'!G:G,'Folha Rainha'!B:B,BASE_DE_NOMES[[#This Row],[Nome]],'Folha Rainha'!F:F,"HORAS FALTAS")+SUMIFS('Folha Rainha'!G:G,'Folha Rainha'!B:B,BASE_DE_NOMES[[#This Row],[Nome]],'Folha Rainha'!F:F,"HORAS FALTAS DSR")+SUMIFS('Folha Rainha'!G:G,'Folha Rainha'!B:B,BASE_DE_NOMES[[#This Row],[Nome]],'Folha Rainha'!F:F,"FALTA DE CAIXA") -> 0 | I165: =SUMIFS('Folha Rainha'!G:G,'Folha Rainha'!B:B,BASE_DE_NOMES[[#This Row],[Nome]],'Folha Rainha'!F:F,"DESCONTO HORAS AFASTADAS")+SUMIFS('Folha Rainha'!G:G,'Folha Rainha'!B:B,BASE_DE_NOMES[[#This Row],[Nome]],'Folha Rainha'!F:F,"DESCONTO HORAS AFASTADAS ACID TRABALHO")+SUMIFS('Folha Rainha'!G:G,'Folha Rainha'!B:B,BASE_DE_NOMES[[#This Row],[Nome]],'Folha Rainha'!F:F,"SALARIO MATERNIDADE") -> 0 | J165: =BASE_DE_NOMES[[#This Row],[C.CHEQUE]]-BASE_DE_NOMES[[#This Row],[FALTAS]]-BASE_DE_NOMES[[#This Row],[DESCONTO ]] -> 0 | K165: =SUMIF(GRATIFICAÇÃO!A:A,BASE_DE_NOMES[[#This Row],[Nome]],GRATIFICAÇÃO!F:F) -> 0 | L165: =SUMIF(PG!A:A,BASE_DE_NOMES[[#This Row],[Nome]],PG!E:E) -> 0 | M165: =SUMIFS('Folha Rainha'!G:G,'Folha Rainha'!B:B,BASE_DE_NOMES[[#This Row],[Nome]],'Folha Rainha'!F:F,"*Quebra*",'Folha Rainha'!F:F,"*QUEBRA*") -> 0 | N165: =SUMIFS('Folha Rainha'!G:G,'Folha Rainha'!B:B,BASE_DE_NOMES[[#This Row],[Nome]],'Folha Rainha'!F:F,"ADC. ANTIGUIDADE") -> 0 | O165: =SUMIFS('Folha Rainha'!G:G,'Folha Rainha'!B:B,BASE_DE_NOMES[[#This Row],[Nome]],'Folha Rainha'!F:F,"*Trienio*") -> 0 | P165: =SUMIFS('Folha Rainha'!G:G,'Folha Rainha'!B:B,BASE_DE_NOMES[[#This Row],[Nome]],'Folha Rainha'!F:F,"*TAXA*") -> 0 | Q165: =SUMIFS('Folha Rainha'!G:G,'Folha Rainha'!B:B,BASE_DE_NOMES[[#This Row],[Nome]],'Folha Rainha'!F:F,"SALARIO FAMILIA")+SUMIFS('Folha Rainha'!G:G,'Folha Rainha'!B:B,BASE_DE_NOMES[[#This Row],[Nome]],'Folha Rainha'!F:F,"Salário Família") -> 0 | R165: =SUMIFS('Folha Rainha'!G:G,'Folha Rainha'!B:B,BASE_DE_NOMES[[#This Row],[Nome]],'Folha Rainha'!F:F,"BOLSA AUXILIO")+SUMIFS('Folha Rainha'!G:G,'Folha Rainha'!B:B,BASE_DE_NOMES[[#This Row],[Nome]],'Folha Rainha'!F:F,"BOLSA AUXILIO AFASTAMENTO DIREITOS INT") -> 0 | S165: =SUMIFS('Folha Rainha'!G:G,'Folha Rainha'!B:B,BASE_DE_NOMES[[#This Row],[Nome]],'Folha Rainha'!F:F,"Vale Transporte")+SUMIFS('Folha Rainha'!G:G,'Folha Rainha'!B:B,BASE_DE_NOMES[[#This Row],[Nome]],'Folha Rainha'!F:F,"VALE TRANSPORTE 6%")+SUMIFS('Folha Rainha'!G:G,'Folha Rainha'!B:B,BASE_DE_NOMES[[#This Row],[Nome]],'Folha Rainha'!F:F,"AUXILIO TRANSPORTE ") -> 0 | T165: =SUMIFS('Folha Rainha'!G:G,'Folha Rainha'!B:B,BASE_DE_NOMES[[#This Row],[Nome]],'Folha Rainha'!F:F,"ASSISTÊNCIA ODONTOLÓGICA")+SUMIFS('Folha Rainha'!G:G,'Folha Rainha'!B:B,BASE_DE_NOMES[[#This Row],[Nome]],'Folha Rainha'!F:F,"ASSIST. ODONTO OUTROS DEPENDENTES")+SUMIFS('Folha Rainha'!G:G,'Folha Rainha'!B:B,BASE_DE_NOMES[[#This Row],[Nome]],'Folha Rainha'!F:F,"AUXILIO PLANO DE BENEFICIOS DEPENDENTES ") -> 0 | U165: =SUMIFS('Folha Rainha'!G:G,'Folha Rainha'!B:B,BASE_DE_NOMES[[#This Row],[Nome]],'Folha Rainha'!F:F,"BOLSA AUXILIO DESCONTO ADIANTAMENTO")+SUMIFS('Folha Rainha'!G:G,'Folha Rainha'!B:B,BASE_DE_NOMES[[#This Row],[Nome]],'Folha Rainha'!F:F,"DESCONTO PLANO DE SAÚDE")+BASE_DE_NOMES[[#This Row],[TX ASSIS. TOTAL]] -> 0 | V165: =BASE_DE_NOMES[[#This Row],[BOLSA DE AUXILIO]]+BASE_DE_NOMES[[#This Row],[VALE TRANSP]]+BASE_DE_NOMES[[#This Row],[PLANO DE SAUDE]]-BASE_DE_NOMES[[#This Row],[DESCONTOS]] -> 0 | W165: =SUMIFS('Folha Rainha'!G:G,'Folha Rainha'!B:B,BASE_DE_NOMES[[#This Row],[Nome]],'Folha Rainha'!F:F,"VALE COMPRAS")+SUMIFS('Folha Rainha'!G:G,'Folha Rainha'!B:B,BASE_DE_NOMES[[#This Row],[Nome]],'Folha Rainha'!F:F,"VALES") -> 0 | X165: =SUMIFS('Folha Rainha'!G:G,'Folha Rainha'!B:B,BASE_DE_NOMES[[#This Row],[Nome]],'Folha Rainha'!F:F,"ABONO CCT SECOFS 2024-2025")+SUMIFS('Folha Rainha'!G:G,'Folha Rainha'!B:B,BASE_DE_NOMES[[#This Row],[Nome]],'Folha Rainha'!F:F,"PARCELA DIFERENÇA 13o CCT")+SUMIFS('Folha Rainha'!G:G,'Folha Rainha'!B:B,BASE_DE_NOMES[[#This Row],[Nome]],'Folha Rainha'!F:F,"CONTRIBUICAO ABONO CCT 2024-2025") -> 0 | Y165: =BASE_DE_NOMES[[#This Row],[TOTAL DE C.CHEQUE]]+BASE_DE_NOMES[[#This Row],[TOTAL DE QUEBRA]]+BASE_DE_NOMES[[#This Row],[ADC. ANTIGUIDADE]]+BASE_DE_NOMES[[#This Row],[TOTAL DE TRIENIO]]+BASE_DE_NOMES[[#This Row],[CCT]] -> 0 | Z165: =BASE_DE_NOMES[[#This Row],[PAGAMENTOS]]+BASE_DE_NOMES[[#This Row],[GRATIFICAÇÃO]] -> 0 | AA165: =_xlfn.XLOOKUP(BASE_DE_NOMES[[#This Row],[NOME2]],Planilha1!C:C,Planilha1!D:D)*Y165 -> 0 | AB165: =BASE_DE_NOMES[[#This Row],[IMPOSTOS]]+BASE_DE_NOMES[[#This Row],[SALARIO BASE]]+BASE_DE_NOMES[[#This Row],[FAMILIA]] -> 0 | AC165: =_xlfn.XLOOKUP(BASE_DE_NOMES[[#This Row],[Razão Social]],Planilha1!B:B,Planilha1!C:C) -> METANÓIA | AD165: =_xlfn.XLOOKUP(BASE_DE_NOMES[[#This Row],[Alocações]],Planilha1!B:B,Planilha1!C:C) -> METANÓIA
X166: =SUBTOTAL(109,BASE_DE_NOMES[CCT]) -> 0

Sheet Planilha1
A1: Nº | B1: DE | C1: PARA | D1: tx
A2: 1 | C2: 21K DECORAÇÕES | D2: 0.2
A3: =A2+1 -> 2 | B3: GENESIS | C3: GENESIS | D3: 0.2
A4: =A3+1 -> 3 | B4: REIS FABRICA | C4: FABRICA | D4: 0.5033
A5: =A4+1 -> 4 | B5: RAINHA HOME | C5: HOME CENTER | D5: 0.2
A6: =A5+1 -> 5 | B6: REIS MATRIZ | C6: SR PASSOS | D6: 0.5033
A7: =A6+1 -> 6 | B7: 15K COMERCIAL | C7: 15 K COMERCIAL | D7: 0.2
A8: =A7+1 -> 7 | B8: FÊNIX | C8: FENIX | D8: 0.2 | F8: "IMPORTOS", each if [Alocação.1] = "REIS FÁBRICA" then 0.5033 else if [Alocação.1] = "REIS MATRIZ" then 0.5033 else if [Alocação.1] = "PSG" then 0.5033 else 0.2 , type number )
A9: =A8+1 -> 8 | B9: METANOIA | C9: METANÓIA | D9: 0.2
A10: =A9+1 -> 9 | B10: PRATTIKA | C10: PRATTIKA | D10: 0.2
A11: =A10+1 -> 10 | B11: RAINHA MAISON | C11: MAISON | D11: 0.2
A12: =A11+1 -> 11 | B12: 10 K DECORACOES | C12: 10k DECORAÇÕES | D12: 0.2
A13: =A12+1 -> 12 | B13: 05K COMERCIAL | C13: 5K DECORAÇÕES | D13: 0.2
A14: =A13+1 -> 13 | B14: AVANTE | C14: AVANTE | D14: 0.2
A15: =A14+1 -> 14 | B15: 30K COMERCIAL | C15: 30 K | D15: 0.2
A16: =A15+1 -> 15 | B16: GRAND CANYON | C16: GRAND CANYON | D16: 0.2
A17: =A16+1 -> 16 | B17: VALE XEL | C17: VALE XEL | D17: 0.2
A18: =A17+1 -> 17 | B18: E-COMMERCE | C18: E-COMMERCE | D18: 0.2
A19: =A18+1 -> 18 | B19: ESCRITORIO | C19: ESCRITORIO | D19: 0.2
A20: =A19+1 -> 19 | B20: 21K FILIAL | C20: 21K FILIAL | D20: 0.2
... A23: =A22+1 -> 22 | B23: ESCRITÓRIO | C23: ESCRITORIO | D23: 0.2
A24: 23 | B24: PSG - CD | C24: PSG | D24: 0.5033
A25: =A24+1 -> 24 | B25: REIS FÁBRICA | C25: FABRICA | D25: 0.5033
A26: =A25+1 -> 25 | B26: RAINHA HOME | C26: GRUPO RAINHA | D26: 0.2
A27: =A26+1 -> 26 | B27: 10K DECORAÇÕES | C27: 10k DECORAÇÕES | D27: 0.2
A28: =A27+1 -> 27 | B28: 15K DECORAÇÕES | C28: 15 K COMERCIAL | D28: 0.2
A29: =A28+1 -> 28 | B29: PSG IMPORTACAO E DISTRIBUICAO TEXTIL LTD | C29: PSG | D29: 0.5033
A30: =A29+1 -> 29 | B30: RAINHA HOME CENTER LTDA | C30: HOME CENTER | D30: 0.2
A31: =A30+1 -> 30 | B31: 10K DECORAÇÕES | C31: 10k DECORAÇÕES | D31: 0.2
A32: =A31+1 -> 31 | B32: 15K DECORAÇÕES | C32: 15 K COMERCIAL | D32: 0.2
A33: =A32+1 -> 32 | B33: 15K DECORAÇÕES | C33: 15 K COMERCIAL | D33: 0.2
A34: =A33+1 -> 33 | B34: 15K DECORAÇÕES | C34: 15 K COMERCIAL | D34: 0.2
A35: =A34+1 -> 34 | B35: 10K DECORAÇÕES | C35: 10k DECORAÇÕES | D35: 0.2
A36: =A35+1 -> 35 | B36: 10K DECORAÇÕES | C36: 10k DECORAÇÕES | D36: 0.2
... A65: =A64+1 -> 64 | B65: PSG IMP | C65: PSG | D65: 0.5033

Sheet BASE DE NOMES (2)
A1: Status | B1: Nome | C1: Função | D1: Razão Social | E1: Alocação | F1: Admissão
A2: COM REGISTRO | B2: GABRIELE SOUZA OLIVEIRA | C2: VENDEDOR (a) | D2: FÊNIX | E2: 05K COMERCIAL | F2: 43238
A3: COM REGISTRO | B3: GILVANIA LOPES FREITAS | C3: VENDEDOR (a) | D3: 05K COMERCIAL | E3: 05K COMERCIAL | F3: 45202
A4: COM REGISTRO | B4: MIGUEL NASCIMENTO DE JESUS | C4: SERVIÇOS GERAIS | D4: PSG | E4: 05K COMERCIAL | F4: 44470
A5: COM REGISTRO | B5: SUZENE DE CARVALHO SILVA E SILVA | C5: CONFERENTE | D5: GENESIS | E5: 05K COMERCIAL | F5: 45110
A6: COM REGISTRO | B6: ADRIANA DE PINHO FRAGA MEIRELES | C6: VENDEDOR (a) | D6: 10K DECORAÇÕES | E6: 10 K DECORACOES | F6: 44361
A7: CONTRATO | B7: CAILA ROBERTA DA COSTA LIMA | C7: ESTAGIARIO (A) | D7: 10K DECORAÇÕES | E7: 10 K DECORACOES | F7: 45267
A8: COM REGISTRO | B8: ELIEYDE COITINHO SILVA | C8: VENDEDOR (a) | D8: 10K DECORAÇÕES | E8: 10 K DECORACOES | F8: 44361
A9: COM REGISTRO | B9: ELLEN QUELLE SANTOS PATROCINIO | C9: CAIXA | D9: 10K DECORAÇÕES | E9: 10 K DECORACOES | F9: 44860
A10: COM REGISTRO | B10: GILBERTO GALDINO DOS SANTOS | C10: SERVIÇOS GERAIS | D10: 10K DECORAÇÕES | E10: 10 K DECORACOES | F10: 42493
A11: COM REGISTRO | B11: LINDE MELLANY BRAGA AZEVEDO | C11: CAIXA | D11: 10K DECORAÇÕES | E11: 10 K DECORACOES | F11: 45231
A12: COM REGISTRO | B12: MARIANA BATISTA DA CRUZ | C12: CAIXA / SUBGERENTE | D12: 10K DECORAÇÕES | E12: 10 K DECORACOES | F12: 44768
A13: COM REGISTRO | B13: MARIVALDA DE LIMA SALES | C13: VENDEDOR (a) | D13: 10K DECORAÇÕES | E13: 10 K DECORACOES | F13: 43175
... A56: COM REGISTRO | B56: LUCIANA SILVA DE SOUZA | C56: VENDEDOR (a) | D56: RAINHA HOME | E56: GENESIS | F56: 43056
B57: MARIA ROSILENE DOS SANTOS LIMA - 24/01/2024 | C57: CAIXA | D57: GENESIS | E57: REIS MATRIZ
A58: SEM REGISTRO | B58: MIGUEL NASCIMENTO DE JESUS FILHO | C58: SERVIÇOS GERAIS | D58: RAINHA HOME | E58: RAINHA MAISON | F58: 45061
A59: COM REGISTRO | B59: SAMARA RAISSA DA PAIXAO CARDOSO | C59: ESTAGIARIO (A) | D59: GENESIS | E59: GENESIS | F59: 45272
A60: COM REGISTRO | B60: VANUZA SILVA DOS REIS | C60: VENDEDOR (a) | D60: GENESIS | E60: GENESIS | F60: 44792
A61: COM REGISTRO | B61: ANNE KAROLINA NASCIMENTO DOS SANTOS | C61: VENDEDOR (a) | D61: GRAND CANYON | E61: GRAND CANYON | F61: 44334
A62: COM REGISTRO | B62: CARIANE RODRIGUES ARAUJO | C62: VENDEDOR (a) | D62: GRAND CANYON | E62: GRAND CANYON | F62: 45180
A63: COM REGISTRO | B63: ELAINE DA SILVA NEVES | C63: VENDEDOR (a) | D63: GRAND CANYON | E63: GRAND CANYON | F63: 44117
A64: COM REGISTRO | B64: IASMIN LUANY PAULINO DE OLIVEIRA | C64: CAIXA | D64: GRAND CANYON | E64: GRAND CANYON | F64: 45180
A65: COM REGISTRO | B65: LEILANA FELICIANO SANTANA | C65: GERENTE DE VENDAS | D65: GRAND CANYON | E65: GRAND CANYON | F65: 43383
A66: COM REGISTRO | B66: LUCILEIDE LOPES | C66: CAIXA | D66: GRAND CANYON | E66: GRAND CANYON | F66: 45252
A67: COM REGISTRO | B67: VITOR MATEUS CARVALHO ROCHA | C67: SERVIÇOS GERAIS | D67: GRAND CANYON | E67: GRAND CANYON | F67: 45355
A68: COM REGISTRO | B68: FABRICIO SOUZA DOS SANTOS | C68: SERVIÇOS GERAIS/VENDAS | D68: METANOIA | E68: METANOIA | F68: 45236
A69: COM REGISTRO | B69: IOLANDA LIMA DA SILVA SANTOS | C69: VENDEDOR (a) | D69: METANOIA | E69: METANOIA | F69: 43199
... A73: COM REGISTRO | B73: ZILDA DA MOTA LIMA SANTOS | C73: VENDEDOR (a) | D73: METANOIA | E73: METANOIA | F73: 42263
B74: HEMILENE SOUZA RIBEIRO | C74: ASSISTENTE DO FINANCEIRO | D74: REIS MATRIZ | E74: ESCRITÓRIO
B75: IRACEMA DE ALMEIDA E SILVA | C75: GERENTE DE VENDAS | D75: GENESIS | E75: RAINHA HOME
B76: IVONETE DE SOUSA NUNES BARBOSA | C76: ENCARREGADA DE FATURAMENTO | D76: REIS MATRIZ | E76: ESCRITÓRIO
B77: IVONISE CARVALHO DE JESUS | C77: SERVIÇOES GERAIS | D77: PSG | E77: ESCRITÓRIO
B78: JENALDO ALVES DO NASCIMENTO | C78: GERENTE FINANCEIRO | D78: GENESIS | E78: ESCRITÓRIO
B79: JOELMA SILVA SANTOS | C79: CONTROLLER | D79: PSG | E79: ESCRITÓRIO
B80: JULIA CAMPOS DE MATOS | C80: ESTAGIARIO (A) | D80: 05K COMERCIAL | E80: ESCRITÓRIO
B81: LAVINIA REIS DE LIMA | C81: ASSISTENTE FINANCEIRO | D81: PSG | E81: ESCRITÓRIO
B82: LUCIANA VIANA COSTA | C82: AUXILIAR ADMINISTRATIVO | D82: RAINHA HOME | E82: ESCRITÓRIO
B83: OLGA DAMASCENO DOS SANTOS MELO | C83: AUXILIAR DE DP | D83: PSG | E83: ESCRITÓRIO
B84: PATRICIA XAVIER CARNEIRO | C84: GERENTE DE RH | D84: PSG | E84: ESCRITÓRIO
B85: ARIANA SANTOS DE OLIVEIRA MAXIMIANO | C85: ASSISTENTE SETOR FISCAL | D85: PSG | E85: ESCRITÓRIO
... B95: SINARIA DE MENEZES PINHEIRO | C95: PRO LABORE | D95: MAISON | E95: ESCRITÓRIO
A96: COM REGISTRO | B96: DJENANE DA SILVA SANTANA | C96: VENDEDOR (a) | D96: RAINHA MAISON | E96: RAINHA HOME | F96: 41093
A97: COM REGISTRO | B97: FERNANDA DA SILVA MASCENA | C97: ESTAGIARIO (A) | D97: RAINHA HOME | E97: RAINHA HOME | F97: 45257
A98: COM REGISTRO | B98: GISELE LIMA DOS SANTOS | C98: ESTAGIARIO (A) | D98: RAINHA HOME | E98: RAINHA HOME | F98: 45272
A99: COM REGISTRO | B99: MARISTELA DALTRO SANTANA BISPO | C99: CAIXA | D99: 05K COMERCIAL | E99: RAINHA HOME | F99: 44117
A100: COM REGISTRO | B100: NORMA NEIDE SOUZA DE JESUS | C100: GERENTE JÚNIOR | D100: FÊNIX | E100: RAINHA HOME | F100: 43349
A101: COM REGISTRO | B101: ROBERTO SALES NEVES | C101: GERENTE DE VENDAS | D101: RAINHA HOME | E101: RAINHA HOME | F101: 42675
A102: COM REGISTRO | B102: ADRIANE AMORIM RIBEIRO | C102: VENDEDOR (a) | D102: GENESIS | E102: REIS MATRIZ | F102: 40575
B103: CAROLAINE SILVA DE ASSIS | C103: CAIXA | D103: REIS MATRIZ | E103: REIS MATRIZ
A104: COM REGISTRO | B104: DANIEL SILVA NUNES | C104: ESTAGIARIO (A) | D104: REIS MATRIZ | E104: REIS MATRIZ | F104: 45236
A105: COM REGISTRO | B105: ELIANE DOS SANTOS SILVA | C105: VENDEDOR (a) | D105: REIS MATRIZ | E105: REIS MATRIZ | F105: 44117
A106: COM REGISTRO | B106: FRANCIELE DOS SANTOS ARAUJO | C106: VENDEDOR (a) | D106: REIS MATRIZ | E106: REIS MATRIZ | F106: 44173
A107: COM REGISTRO | B107: FRANCISCA SELMA SANTOS DE SALES | C107: VENDEDOR (a) | D107: PRATTIKA | E107: REIS MATRIZ | F107: 44874
B108: GEOVANA LYSSA BARROS SANTOS | C108: CAIXA | D108: REIS MATRIZ | E108: REIS MATRIZ
A109: COM REGISTRO | B109: GILBERTO DOS SANTOS | C109: SUPERVISOR | D109: PSG | E109: REIS MATRIZ | F109: 45017
B110: GISELE TEIXEIRA DE SOUZA DIAS | C110: VENDEDORA | D110: FÊNIX | E110: REIS MATRIZ
A111: COM REGISTRO | B111: ISRAELLE DOS SANTOS COSTA | C111: ESTAGIARIO (A) | D111: REIS MATRIZ | E111: REIS MATRIZ | F111: 45252
A112: COM REGISTRO | B112: LAIANE DOS SANTOS MELO | C112: VENDEDOR (a) | D112: REIS MATRIZ | E112: REIS MATRIZ | F112: 44928
A113: COM REGISTRO | B113: MARIA JOSE CONI FONSECA | C113: VENDEDOR (a) | D113: REIS MATRIZ | E113: REIS MATRIZ | F113: 40210
A114: COM REGISTRO | B114: MARIA ROSILENE DOS SANTOS LIMA | C114: CAIXA | D114: GENESIS | E114: REIS MATRIZ | F114: 45330
A115: COM REGISTRO | B115: NAIRA COSTA SANTANA | C115: CAIXA | D115: REIS MATRIZ | E115: REIS MATRIZ | F115: 45202
A116: COM REGISTRO | B116: NATIELE DE ALMEIDA BASTOS | C116: VENDEDOR (a) | D116: REIS MATRIZ | E116: REIS MATRIZ | F116: 41974
A117: COM REGISTRO | B117: SANDRA PEREIRA SALES | C117: VENDEDOR (a) | D117: REIS MATRIZ | E117: REIS MATRIZ | F117: 40210
A118: COM REGISTRO | B118: SIDNEA SOARES PINTO | C118: VENDEDOR (a) | D118: FÊNIX | E118: REIS MATRIZ | F118: 42320
A119: COM REGISTRO | B119: UELITON DA SILVA DE JESUS | C119: SERVIÇOS GERAIS | D119: REIS MATRIZ | E119: GENESIS | F119: 43437
A120: COM REGISTRO | B120: VALDETE DA SILVA AMORIM | C120: GERENTE DE VENDAS | D120: 10K DECORAÇÕES | E120: REIS MATRIZ | F120: 44470
A121: COM REGISTRO | B121: VALDILENE DOS SANTOS BACELAR | C121: VENDEDOR (a) | D121: REIS MATRIZ | E121: REIS MATRIZ | F121: 41775
A122: COM REGISTRO | B122: ANA PAULA NEVES DA SILVA LEITE | C122: VENDEDOR (a) | D122: RAINHA MAISON | E122: RAINHA MAISON | F122: 44844
... A182: COM REGISTRO | B182: WIVINA GONZAGA DIAS | C182: COSTUREIRO (A) | D182: VALE XEL | E182: REIS FÁBRICA | F182: 44774
A183: COM REGISTRO | B183: LUCAS RAMOS CATARINO | C183: AUX TI | D183: PRATTIKA | E183: RAINHA HOME
A184: COM REGISTRO | B184: DORIVALDO SANTOS ARAUJO | C184: CONFERENTE | D184: RAINHA HOME | E184: RAINHA HOME | F184: 44774
A185: COM REGISTRO | B185: VALDICK SANTOS LEAO | C185: MOTORISTA | D185: RAINHA MAISON | E185: RAINHA HOME | F185: 40940
A186: COM REGISTRO | B186: NATERCIO PEREIRA SANTANA | C186: MOTORISTA | D186: REIS MATRIZ | E186: RAINHA HOME | F186: 44762

Sheet Folha Rainha
A1: LOJAS | B1: Nome | C1: Cargo | D1: Adm: | E1: Situação | F1: Atributo | G1: Valor
A2: 716 - PRATTIKA COMERCIAL DE UTILIDADES DOMESTI | B2: LUCAS RAMOS CATARINO | C2: AUXILIAR DE TI | D2: 44844 | E2: Transferido | F2: SALDO DE SALARIO HORAS | G2: 2110 | J2: =#REF!/#REF! -> #REF!
A3: 716 - PRATTIKA COMERCIAL DE UTILIDADES DOMESTI | B3: LUCAS RAMOS CATARINO | C3: AUXILIAR DE TI | D3: 44844 | E3: Transferido | F3: ESTORNO DESC PROV EMPRESTIMO TRAB ADIANT | G3: 114.04 | J3: =#REF!/#REF! -> #REF!
A4: 716 - PRATTIKA COMERCIAL DE UTILIDADES DOMESTI | B4: LUCAS RAMOS CATARINO | C4: AUXILIAR DE TI | D4: 44844 | E4: Transferido | F4: LIQUIDO RESCISAO | G4: 824.39 | J4: =#REF!/#REF! -> #REF!
A5: 716 - PRATTIKA COMERCIAL DE UTILIDADES DOMESTI | B5: LUCAS RAMOS CATARINO | C5: AUXILIAR DE TI | D5: 44844 | E5: Transferido | F5: VALE COMPRAS | G5: 103.4 | J5: =#REF!/#REF! -> #REF!
A6: 716 - PRATTIKA COMERCIAL DE UTILIDADES DOMESTI | B6: LUCAS RAMOS CATARINO | C6: AUXILIAR DE TI | D6: 44844 | E6: Transferido | F6: DESC.ADIANT.SALARIAL | G6: 844 | J6: =#REF!/#REF! -> #REF!
A7: 716 - PRATTIKA COMERCIAL DE UTILIDADES DOMESTI | B7: LUCAS RAMOS CATARINO | C7: AUXILIAR DE TI | D7: 44844 | E7: Transferido | F7: DESC. EMPREST. CREDITO TRABALHADOR 1 | G7: 285.12 | J7: =#REF!/#REF! -> #REF!
A8: 716 - PRATTIKA COMERCIAL DE UTILIDADES DOMESTI | B8: LUCAS RAMOS CATARINO | C8: AUXILIAR DE TI | D8: 44844 | E8: Transferido | F8: Salário: | G8: 2110 | J8: =#REF!/#REF! -> #REF!
A9: 728 - RAINHA MAISON COMERCIAL LTDA | B9: ANA PAULA NEVES DA SILVA LEITE | C9: VENDEDOR (A) | D9: 44844 | E9: Trabalhando | F9: HORAS NORMAIS | G9: 1660 | J9: =#REF!/#REF! -> #REF!
A10: 728 - RAINHA MAISON COMERCIAL LTDA | B10: ANA PAULA NEVES DA SILVA LEITE | C10: VENDEDOR (A) | D10: 44844 | E10: Trabalhando | F10: CONTRIBUICAO NEGOCIAL ASSISTENCIAL | G10: 20 | J10: =#REF!/#REF! -> #REF!
A11: 728 - RAINHA MAISON COMERCIAL LTDA | B11: ANA PAULA NEVES DA SILVA LEITE | C11: VENDEDOR (A) | D11: 44844 | E11: Trabalhando | F11: DESC.ADIANT.SALARIAL | G11: 664 | J11: =#REF!/#REF! -> #REF!
A12: 728 - RAINHA MAISON COMERCIAL LTDA | B12: ANA PAULA NEVES DA SILVA LEITE | C12: VENDEDOR (A) | D12: 44844 | E12: Trabalhando | F12: VALE TRANSPORTE 6% | G12: 99.6 | J12: =#REF!/#REF! -> #REF!
A13: 728 - RAINHA MAISON COMERCIAL LTDA | B13: ANA PAULA NEVES DA SILVA LEITE | C13: VENDEDOR (A) | D13: 44844 | E13: Trabalhando | F13: AUXILIO PLANO DE BENEFICIOS DEPENDENTES | G13: 16.9 | J13: =#REF!/#REF! -> #REF!
... A109: 731 - REIS DO NORDESTE CAMA MESA E BANHO LTDA | B109: VALDILENE DOS SANTOS BACELAR | C109: VENDEDOR (A) SOCIO-GERENTE | D109: 41775 | E109: Trabalhando | F109: VALE TRANSPORTE 6% | G109: 99.6 | J109: =#REF!/#REF! -> #REF!
A110: 731 - REIS DO NORDESTE CAMA MESA E BANHO LTDA | B110: VALDILENE DOS SANTOS BACELAR | C110: VENDEDOR (A) SOCIO-GERENTE | D110: 41775 | E110: Trabalhando | F110: Salário: | G110: 1660 | K110: =Folha_Rainha[[#Totals],[Valor]]-#REF! -> #REF! | O110: =#REF!/#REF! -> #REF!
A111: 731 - REIS DO NORDESTE CAMA MESA E BANHO LTDA | B111: VALDILENE DOS SANTOS BACELAR | C111: VENDEDOR (A) SOCIO-GERENTE | D111: 41775 | E111: Trabalhando | F111: Salário: | G111: 5559 | O111: =#REF!/#REF! -> #REF!
A112: 934 - REIS DO NORDESTE CAMA MESA E BANHO LTDA | B112: ALBERTO DO NASCIMENTO SANTOS | C112: EMBALADOR ( A ) | D112: 43222 | E112: Férias | F112: HORAS NORMAIS | G112: 1366.2 | O112: =#REF!/#REF! -> #REF!
A113: 934 - REIS DO NORDESTE CAMA MESA E BANHO LTDA | B113: ALBERTO DO NASCIMENTO SANTOS | C113: EMBALADOR ( A ) | D113: 43222 | E113: Férias | F113: DESC.ADIANT.SALARIAL | G113: 607.2 | O113: =#REF!/#REF! -> #REF!
A114: 934 - REIS DO NORDESTE CAMA MESA E BANHO LTDA | B114: ALBERTO DO NASCIMENTO SANTOS | C114: EMBALADOR ( A ) | D114: 43222 | E114: Férias | F114: Salário: | G114: 1518 | O114: =#REF!/#REF! -> #REF!
A115: 934 - REIS DO NORDESTE CAMA MESA E BANHO LTDA | B115: ALESSANDRO BATISTA DA ROCHA | C115: EMBALADOR ( A ) | D115: 44637 | E115: Trabalhando | F115: HORAS NORMAIS | G115: 1518 | O115: =#REF!/#REF! -> #REF!
A116: 934 - REIS DO NORDESTE CAMA MESA E BANHO LTDA | B116: ALESSANDRO BATISTA DA ROCHA | C116: EMBALADOR ( A ) | D116: 44637 | E116: Trabalhando | F116: DESC.ADIANT.SALARIAL | G116: 607.2 | O116: =#REF!/#REF! -> #REF!
A117: 934 - REIS DO NORDESTE CAMA MESA E BANHO LTDA | B117: ALESSANDRO BATISTA DA ROCHA | C117: EMBALADOR ( A ) | D117: 44637 | E117: Trabalhando | F117: Salário: | G117: 1518 | O117: =#REF!/#REF! -> #REF!
A118: 934 - REIS DO NORDESTE CAMA MESA E BANHO LTDA | B118: ANA PAULA JESUS DOS SANTOS | C118: COSTUREIRO ( A ) | D118: 45731 | E118: Trabalhando | F118: HORAS NORMAIS | G118: 1518 | O118: =#REF!/#REF! -> #REF!
A119: 934 - REIS DO NORDESTE CAMA MESA E BANHO LTDA | B119: ANA PAULA JESUS DOS SANTOS | C119: COSTUREIRO ( A ) | D119: 45731 | E119: Trabalhando | F119: DESC.ADIANT.SALARIAL | G119: 607.2 | O119: =#REF!/#REF! -> #REF!
A120: 934 - REIS DO NORDESTE CAMA MESA E BANHO LTDA | B120: ANA PAULA JESUS DOS SANTOS | C120: COSTUREIRO ( A ) | D120: 45731 | E120: Trabalhando | F120: Salário: | G120: 1518 | O120: =#REF!/#REF! -> #REF!
A121: 934 - REIS DO NORDESTE CAMA MESA E BANHO LTDA | B121: BRUNA DOS SANTOS MATOS | C121: COSTUREIRO ( A ) | D121: 45731 | E121: Trabalhando | F121: HORAS NORMAIS | G121: 1518 | O121: =#REF!/#REF! -> #REF!
A122: 934 - REIS DO NORDESTE CAMA MESA E BANHO LTDA | B122: BRUNA DOS SANTOS MATOS | C122: COSTUREIRO ( A ) | D122: 45731 | E122: Trabalhando | F122: DESC.ADIANT.SALARIAL | G122: 607.2 | O122: =#REF!/#REF! -> #REF!
... A224: 934 - REIS DO NORDESTE CAMA MESA E BANHO LTDA | B224: MARIA VALERIA NASCIMENTO DE JESUS | C224: COSTUREIRO ( A ) | D224: 45390 | E224: Trabalhando | F224: Salário: | G224: 1518 | O224: =#REF!/#REF! -> #REF!
A225: 934 - REIS DO NORDESTE CAMA MESA E BANHO LTDA | B225: MARINALVA ALVES DE JESUS | C225: COSTUREIRO ( A ) | D225: 45390 | E225: Trabalhando | F225: HORAS NORMAIS | G225: 1518 | AI225: =#REF!/#REF! -> #REF!
A226: 934 - REIS DO NORDESTE CAMA MESA E BANHO LTDA | B226: MARINALVA ALVES DE JESUS | C226: COSTUREIRO ( A ) | D226: 45390 | E226: Trabalhando | F226: DESC.ADIANT.SALARIAL | G226: 607.2 | AI226: =#REF!/#REF! -> #REF!
A227: 934 - REIS DO NORDESTE CAMA MESA E BANHO LTDA | B227: MARINALVA ALVES DE JESUS | C227: COSTUREIRO ( A ) | D227: 45390 | E227: Trabalhando | F227: Salário: | G227: 1518 | AI227: =#REF!/#REF! -> #REF!
A228: 934 - REIS DO NORDESTE CAMA MESA E BANHO LTDA | B228: MARTA DE SOUZA AMADO | C228: AUXILIAR DE ESCRITORIO | D228: 45597 | E228: Trabalhando | F228: HORAS NORMAIS | G228: 1518 | AI228: =#REF!/#REF! -> #REF!
A229: 934 - REIS DO NORDESTE CAMA MESA E BANHO LTDA | B229: MARTA DE SOUZA AMADO | C229: AUXILIAR DE ESCRITORIO | D229: 45597 | E229: Trabalhando | F229: DESC.ADIANT.SALARIAL | G229: 607.2 | AI229: =#REF!/#REF! -> #REF!
A230: 934 - REIS DO NORDESTE CAMA MESA E BANHO LTDA | B230: MARTA DE SOUZA AMADO | C230: AUXILIAR DE ESCRITORIO | D230: 45597 | E230: Trabalhando | F230: Salário: | G230: 1518 | AI230: =#REF!/#REF! -> #REF!
A231: 934 - REIS DO NORDESTE CAMA MESA E BANHO LTDA | B231: MARTA ORTENCIA OLIVEIRA DA SILVA | C231: COSTUREIRO ( A ) | D231: 45674 | E231: Trabalhando | F231: HORAS NORMAIS | G231: 1518 | AI231: =#REF!/#REF! -> #REF!
A232: 934 - REIS DO NORDESTE CAMA MESA E BANHO LTDA | B232: MARTA ORTENCIA OLIVEIRA DA SILVA | C232: COSTUREIRO ( A ) | D232: 45674 | E232: Trabalhando | F232: DESC.ADIANT.SALARIAL | G232: 607.2 | AI232: =#REF!/#REF! -> #REF!
A233: 934 - REIS DO NORDESTE CAMA MESA E BANHO LTDA | B233: MARTA ORTENCIA OLIVEIRA DA SILVA | C233: COSTUREIRO ( A ) | D233: 45674 | E233: Trabalhando | F233: Salário: | G233: 1518 | AI233: =#REF!/#REF! -> #REF!
A234: 934 - REIS DO NORDESTE CAMA MESA E BANHO LTDA | B234: MAURI SANTOS SANTANA | C234: EMBALADOR ( A ) | D234: 44216 | E234: Trabalhando | F234: HORAS NORMAIS | G234: 1518 | AI234: =#REF!/#REF! -> #REF!
A235: 934 - REIS DO NORDESTE CAMA MESA E BANHO LTDA | B235: MAURI SANTOS SANTANA | C235: EMBALADOR ( A ) | D235: 44216 | E235: Trabalhando | F235: DESC.ADIANT.SALARIAL | G235: 607.2 | AI235: =#REF!/#REF! -> #REF!
A236: 934 - REIS DO NORDESTE CAMA MESA E BANHO LTDA | B236: MAURI SANTOS SANTANA | C236: EMBALADOR ( A ) | D236: 44216 | E236: Trabalhando | F236: Salário: | G236: 1518 | AI236: =#REF!/#REF! -> #REF!
... A244: 934 - REIS DO NORDESTE CAMA MESA E BANHO LTDA | B244: RAYANE MONTEIRO REIS | C244: COSTUREIRO ( A ) | D244: 45681 | E244: Trabalhando | F244: HORAS NORMAIS | G244: 1518 | AI244: =#REF!/#REF! -> #REF!
A245: 934 - REIS DO NORDESTE CAMA MESA E BANHO LTDA | B245: RAYANE MONTEIRO REIS | C245: COSTUREIRO ( A ) | D245: 45681 | E245: Trabalhando | F245: DESC.ADIANT.SALARIAL | G245: 607.2
A246: 934 - REIS DO NORDESTE CAMA MESA E BANHO LTDA | B246: RAYANE MONTEIRO REIS | C246: COSTUREIRO ( A ) | D246: 45681 | E246: Trabalhando | F246: Salário: | G246: 1518
A247: 934 - REIS DO NORDESTE CAMA MESA E BANHO LTDA | B247: SABRINA DE ARAUJO DOREA | C247: COSTUREIRO ( A ) | D247: 45748 | E247: Trabalhando | F247: HORAS NORMAIS | G247: 1518
A248: 934 - REIS DO NORDESTE CAMA MESA E BANHO LTDA | B248: SABRINA DE ARAUJO DOREA | C248: COSTUREIRO ( A ) | D248: 45748 | E248: Trabalhando | F248: DEVOLUCAO DESCONTO INDEVIDO | G248: 117.3
A249: 934 - REIS DO NORDESTE CAMA MESA E BANHO LTDA | B249: SABRINA DE ARAUJO DOREA | C249: COSTUREIRO ( A ) | D249: 45748 | E249: Trabalhando | F249: DESC.ADIANT.SALARIAL | G249: 607.2
A250: 934 - REIS DO NORDESTE CAMA MESA E BANHO LTDA | B250: SABRINA DE ARAUJO DOREA | C250: COSTUREIRO ( A ) | D250: 45748 | E250: Trabalhando | F250: Salário: | G250: 1518
A251: 934 - REIS DO NORDESTE CAMA MESA E BANHO LTDA | B251: VALERIA BATISTA DOS SANTOS | C251: COSTUREIRO ( A ) | D251: 45731 | E251: Trabalhando | F251: HORAS NORMAIS | G251: 1518
A252: 934 - REIS DO NORDESTE CAMA MESA E BANHO LTDA | B252: VALERIA BATISTA DOS SANTOS | C252: COSTUREIRO ( A ) | D252: 45731 | E252: Trabalhando | F252: DESC.ADIANT.SALARIAL | G252: 607.2
A253: 934 - REIS DO NORDESTE CAMA MESA E BANHO LTDA | B253: VALERIA BATISTA DOS SANTOS | C253: COSTUREIRO ( A ) | D253: 45731 | E253: Trabalhando | F253: Salário: | G253: 1518
A254: 934 - REIS DO NORDESTE CAMA MESA E BANHO LTDA | B254: VERONICA JESUS DOS SANTOS | C254: COSTUREIRO ( A ) | D254: 45673 | E254: Trabalhando | F254: HORAS NORMAIS | G254: 1518
A255: 934 - REIS DO NORDESTE CAMA MESA E BANHO LTDA | B255: VERONICA JESUS DOS SANTOS | C255: COSTUREIRO ( A ) | D255: 45673 | E255: Trabalhando | F255: DESC.ADIANT.SALARIAL | G255: 607.2
A256: 934 - REIS DO NORDESTE CAMA MESA E BANHO LTDA | B256: VERONICA JESUS DOS SANTOS | C256: COSTUREIRO ( A ) | D256: 45673 | E256: Trabalhando | F256: Salário: | G256: 1518
... A600: 1919 - VALE XEL COMERCIAL DE CAMA MESA E BANHO | B600: TAIUANA SANTOS SOARES | C600: COSTUREIRA (O) | D600: 45110 | E600: Demitido | F600: Salário: | G600: 1518
A601: GENESIS COML CAMA MESA E BANHO LTDA | B601: ADRIANE AMORIM RIBEIRO | C601: VENDEDOR(A) | D601: 40575 | F601: Férias | G601: 1604.67
A602: GENESIS COML CAMA MESA E BANHO LTDA | B602: ADRIANE AMORIM RIBEIRO | C602: VENDEDOR(A) | D602: 40575 | F602: Trienio 5% | G602: 257.3
A603: GENESIS COML CAMA MESA E BANHO LTDA | B603: ADRIANE AMORIM RIBEIRO | C603: VENDEDOR(A) | D603: 40575 | F603: Adiantamento Salarial | G603: 22.13
A604: GENESIS COML CAMA MESA E BANHO LTDA | B604: ADRIANE AMORIM RIBEIRO | C604: VENDEDOR(A) | D604: 40575 | F604: 1/3 Férias | G604: 615.12
A605: GENESIS COML CAMA MESA E BANHO LTDA | B605: ADRIANE AMORIM RIBEIRO | C605: VENDEDOR(A) | D605: 40575 | F605: Vale Transporte | G605: 6.64
A606: GENESIS COML CAMA MESA E BANHO LTDA | B606: ADRIANE AMORIM RIBEIRO | C606: VENDEDOR(A) | D606: 40575 | F606: INSS Férias | G606: 198.67
A607: GENESIS COML CAMA MESA E BANHO LTDA | B607: ADRIANE AMORIM RIBEIRO | C607: VENDEDOR(A) | D607: 40575 | F607: Salario Total | G607: 1660
A608: GENESIS COML CAMA MESA E BANHO LTDA | B608: ADRIANE AMORIM RIBEIRO | C608: VENDEDOR(A) | D608: 40575 | F608: Salário Base | G608: 110.67
A609: GENESIS COML CAMA MESA E BANHO LTDA | B609: AILTON LUCENA | C609: GERENTE DE VENDAS | D609: 39052 | F609: Trienio 5% | G609: 644.51
A610: GENESIS COML CAMA MESA E BANHO LTDA | B610: AILTON LUCENA | C610: GERENTE DE VENDAS | D610: 39052 | F610: Adiantamento Salarial | G610: 1718.71
A611: GENESIS COML CAMA MESA E BANHO LTDA | B611: AILTON LUCENA | C611: GERENTE DE VENDAS | D611: 39052 | F611: IRRF Folha | G611: 299.68
A612: GENESIS COML CAMA MESA E BANHO LTDA | B612: AILTON LUCENA | C612: GERENTE DE VENDAS | D612: 39052 | F612: 32 | G612: 4296.77
... A706: FENIX COML DE CAMA MESA E BANHO LTDA | B706: NORMA NEIDE SOUZA DE JESUS | C706: GERENTE JUNIOR | D706: 43349 | F706: Salário Base | G706: 2615.26
A707: FENIX COML DE CAMA MESA E BANHO LTDA | B707: SIDNEA SOARES PINTO | C707: CONFERENTE | F707: Salario Total | G707: 1660
G708: =SUBTOTAL(109,Folha_Rainha[Valor]) -> 15450.6

Sheet Planilha2
A1: Funcionarios
A2: ADRIANA CLEIDE ALVES FIGUEREDO SANTOS | B2: =_xlfn.XLOOKUP(A2,'BASE DE NOMES'!A:A,'BASE DE NOMES'!A:A) -> #N/A
A3: ADRIANE AMORIM RIBEIRO | B3: =_xlfn.XLOOKUP(A3,'BASE DE NOMES'!A:A,'BASE DE NOMES'!A:A) -> #N/A
A4: AILTON LUCENA | B4: =_xlfn.XLOOKUP(A4,'BASE DE NOMES'!A:A,'BASE DE NOMES'!A:A) -> AILTON LUCENA
A5: ALBERTO DO NASCIMENTO SANTOS | B5: =_xlfn.XLOOKUP(A5,'BASE DE NOMES'!A:A,'BASE DE NOMES'!A:A) -> ALBERTO DO NASCIMENTO SANTOS
A6: ALDA COUTINHO DA SILVA | B6: =_xlfn.XLOOKUP(A6,'BASE DE NOMES'!A:A,'BASE DE NOMES'!A:A) -> #N/A
A7: ALESSANDRO BATISTA DA ROCHA | B7: =_xlfn.XLOOKUP(A7,'BASE DE NOMES'!A:A,'BASE DE NOMES'!A:A) -> ALESSANDRO BATISTA DA ROCHA
A8: ALINE DE SOUZA SANTOS | B8: =_xlfn.XLOOKUP(A8,'BASE DE NOMES'!A:A,'BASE DE NOMES'!A:A) -> ALINE DE SOUZA SANTOS
A9: ANA PAULA JESUS DOS SANTOS | B9: =_xlfn.XLOOKUP(A9,'BASE DE NOMES'!A:A,'BASE DE NOMES'!A:A) -> ANA PAULA JESUS DOS SANTOS
A10: ANA PAULA NEVES DA SILVA LEITE | B10: =_xlfn.XLOOKUP(A10,'BASE DE NOMES'!A:A,'BASE DE NOMES'!A:A) -> ANA PAULA NEVES DA SILVA LEITE
A11: ANADILZA ALMEIDA SANTOS | B11: =_xlfn.XLOOKUP(A11,'BASE DE NOMES'!A:A,'BASE DE NOMES'!A:A) -> ANADILZA ALMEIDA SANTOS
A12: ANALIA GUIMARAES MARQUES | B12: =_xlfn.XLOOKUP(A12,'BASE DE NOMES'!A:A,'BASE DE NOMES'!A:A) -> ANALIA GUIMARAES MARQUES
A13: ANNE KAROLINA NASCIMENTO DOS SANTOS | B13: =_xlfn.XLOOKUP(A13,'BASE DE NOMES'!A:A,'BASE DE NOMES'!A:A) -> #N/A
... A151: ZILDA DA MOTA LIMA SANTOS | B151: =_xlfn.XLOOKUP(A151,'BASE DE NOMES'!A:A,'BASE DE NOMES'!A:A) -> #N/A
